[
  {
    "ecommerce": {
      "rowCategory": "small_teaser",
      "rowId": "na",
      "rowName": "Staffel 0"
    },
    "id": null,
    "label": null,
    "moduleLayout": "format_episode",
    "moduleUrl": "/module/teaserrow/format/episode/20190",
    "type": "teaserrow",
    "items": [
      {
        "buttons": [
          {
            "display": true,
            "formatId": 20190,
            "text": null,
            "type": "favorites"
          },
          {
            "display": true,
            "text": "Jetzt streamen",
            "type": "play",
            "url": "/filme/das-kleine-rentier-und-sein-erstes-weihnachten-20190"
          }
        ],
        "ecommerce": {
          "teaserFormatName": "Das kleine Rentier und sein erstes Weihnachten",
          "teaserId": "film_4323681",
          "teaserName": "Das kleine Rentier und sein erstes Weihnachten | Das kleine Rentier und sein erstes Weihnachten",
          "teaserPayType": "paid",
          "teaserType": "film",
          "teaserGenre": "Dokumentation",
          "cluster": [],
          "classification": [],
          "teaserEpisodeAirtime": "GEO WILD",
          "teaserEpisodeName": "Das kleine Rentier und sein erstes Weihnachten"
        },
        "fsk": {
          "isVisible": false,
          "label": "ab 0",
          "minAge": 0
        },
        "headline": "Das kleine Rentier und sein erstes Weihnachten",
        "id": 4323681,
        "images": [
          {
            "dimension": "1x",
            "src": "https://ais-cf.tvnow.de/tvnow/movie/4323681/300x0/das-kleine-rentier-und-sein-erstes-weihnachten.jpg",
            "path": "https://ais-cf.tvnow.de/tvnow/movie/4323681/",
            "filename": "das-kleine-rentier-und-sein-erstes-weihnachten"
          },
          {
            "dimension": "2x",
            "src": "https://ais-cf.tvnow.de/tvnow/movie/4323681/600x0/das-kleine-rentier-und-sein-erstes-weihnachten.jpg",
            "path": "https://ais-cf.tvnow.de/tvnow/movie/4323681/",
            "filename": "das-kleine-rentier-und-sein-erstes-weihnachten"
          },
          {
            "dimension": "4x",
            "src": "https://ais-cf.tvnow.de/tvnow/movie/4323681/1200x0/das-kleine-rentier-und-sein-erstes-weihnachten.jpg",
            "path": "https://ais-cf.tvnow.de/tvnow/movie/4323681/",
            "filename": "das-kleine-rentier-und-sein-erstes-weihnachten"
          }
        ],
        "imagesHover": [
          {
            "dimension": "1x",
            "src": "https://ais-cf.tvnow.de/tvnow/movie/4323681/300x0/das-kleine-rentier-und-sein-erstes-weihnachten.jpg",
            "path": "https://ais-cf.tvnow.de/tvnow/movie/4323681/",
            "filename": "das-kleine-rentier-und-sein-erstes-weihnachten"
          },
          {
            "dimension": "2x",
            "src": "https://ais-cf.tvnow.de/tvnow/movie/4323681/600x0/das-kleine-rentier-und-sein-erstes-weihnachten.jpg",
            "path": "https://ais-cf.tvnow.de/tvnow/movie/4323681/",
            "filename": "das-kleine-rentier-und-sein-erstes-weihnachten"
          },
          {
            "dimension": "4x",
            "src": "https://ais-cf.tvnow.de/tvnow/movie/4323681/1200x0/das-kleine-rentier-und-sein-erstes-weihnachten.jpg",
            "path": "https://ais-cf.tvnow.de/tvnow/movie/4323681/",
            "filename": "das-kleine-rentier-und-sein-erstes-weihnachten"
          }
        ],
        "isPremium": true,
        "overlays": [
          "premium"
        ],
        "seoUrl": "das-kleine-rentier-und-sein-erstes-weihnachten",
        "subheadline": "Das kleine Rentier und sein erstes Weihnachten",
        "text": "Staffel  | GEO WILD",
        "type": "film",
        "url": "/filme/das-kleine-rentier-und-sein-erstes-weihnachten-20190",
        "videoId": 4323681
      }
    ],
    "format_navigation": {
      "season": 0
    },
    "navigationType": "season"
  }
]