[
  {
    "ecommerce": {
      "rowCategory": "small_teaser",
      "rowId": "na",
      "rowName": "Staffel 1"
    },
    "id": null,
    "label": null,
    "moduleLayout": "format_episode",
    "moduleUrl": "/module/teaserrow/format/episode/2011",
    "type": "teaserrow",
    "items": [
      {
        "buttons": [
          {
            "display": true,
            "formatId": 2011,
            "text": null,
            "type": "favorites"
          },
          {
            "display": true,
            "text": "Jetzt ansehen",
            "type": "play",
            "url": "/shows/hausenblas-staubsauger-vertreter-deluxe-2011/staffel-1/episode-1-episode-0001-83523"
          }
        ],
        "ecommerce": {
          "teaserFormatName": "Hausenblas - Staubsauger-Vertreter deluxe ",
          "teaserId": "show_episode_83523",
          "teaserName": "Hausenblas - Staubsauger-Vertreter deluxe  | Staffel 1 | Folge 1 | Episode 0001",
          "teaserPayType": "paid",
          "teaserType": "show_episode",
          "teaserGenre": "Real Life",
          "cluster": [
            "Lifestyle"
          ],
          "classification": [],
          "teaserSeason": "Staffel 1",
          "teaserEpisodeNumber": "Folge 1",
          "teaserEpisodeAirtime": "Mo. 03.09.2018, 22:15 Uhr",
          "teaserEpisodeName": "Episode 0001"
        },
        "fsk": {
          "isVisible": false,
          "label": "ab 0",
          "minAge": 0
        },
        "headline": "Episode 0001",
        "id": 83523,
        "images": [
          {
            "dimension": "1x",
            "src": "https://ais-cf.tvnow.de/tvnow/movie/83523/300x0/episode-0001.jpg",
            "path": "https://ais-cf.tvnow.de/tvnow/movie/83523/",
            "filename": "episode-0001"
          },
          {
            "dimension": "2x",
            "src": "https://ais-cf.tvnow.de/tvnow/movie/83523/600x0/episode-0001.jpg",
            "path": "https://ais-cf.tvnow.de/tvnow/movie/83523/",
            "filename": "episode-0001"
          },
          {
            "dimension": "4x",
            "src": "https://ais-cf.tvnow.de/tvnow/movie/83523/1200x0/episode-0001.jpg",
            "path": "https://ais-cf.tvnow.de/tvnow/movie/83523/",
            "filename": "episode-0001"
          }
        ],
        "imagesHover": [
          {
            "dimension": "1x",
            "src": "https://ais-cf.tvnow.de/tvnow/movie/83523/300x0/episode-0001.jpg",
            "path": "https://ais-cf.tvnow.de/tvnow/movie/83523/",
            "filename": "episode-0001"
          },
          {
            "dimension": "2x",
            "src": "https://ais-cf.tvnow.de/tvnow/movie/83523/600x0/episode-0001.jpg",
            "path": "https://ais-cf.tvnow.de/tvnow/movie/83523/",
            "filename": "episode-0001"
          },
          {
            "dimension": "4x",
            "src": "https://ais-cf.tvnow.de/tvnow/movie/83523/1200x0/episode-0001.jpg",
            "path": "https://ais-cf.tvnow.de/tvnow/movie/83523/",
            "filename": "episode-0001"
          }
        ],
        "isPremium": true,
        "overlays": [
          "premium"
        ],
        "seoUrl": "hausenblas-staubsauger-vertreter-deluxe",
        "subheadline": "Episode 0001",
        "text": "Staffel 1, Folge 1 | Mo. 03.09.2018, 22:15 Uhr",
        "type": "show",
        "url": "/shows/hausenblas-staubsauger-vertreter-deluxe-2011/staffel-1/episode-1-episode-0001-83523",
        "videoId": 83523
      },
      {
        "buttons": [
          {
            "display": true,
            "formatId": 2011,
            "text": null,
            "type": "favorites"
          },
          {
            "display": true,
            "text": "Jetzt ansehen",
            "type": "play",
            "url": "/shows/hausenblas-staubsauger-vertreter-deluxe-2011/staffel-1/episode-2-episode-0002-84453"
          }
        ],
        "ecommerce": {
          "teaserFormatName": "Hausenblas - Staubsauger-Vertreter deluxe ",
          "teaserId": "show_episode_84453",
          "teaserName": "Hausenblas - Staubsauger-Vertreter deluxe  | Staffel 1 | Folge 2 | Episode 0002",
          "teaserPayType": "paid",
          "teaserType": "show_episode",
          "teaserGenre": "Real Life",
          "cluster": [
            "Lifestyle"
          ],
          "classification": [],
          "teaserSeason": "Staffel 1",
          "teaserEpisodeNumber": "Folge 2",
          "teaserEpisodeAirtime": "Mo. 03.09.2018, 23:10 Uhr",
          "teaserEpisodeName": "Episode 0002"
        },
        "fsk": {
          "isVisible": false,
          "label": "ab 0",
          "minAge": 0
        },
        "headline": "Episode 0002",
        "id": 84453,
        "images": [
          {
            "dimension": "1x",
            "src": "https://ais-cf.tvnow.de/tvnow/movie/84453/300x0/episode-0002.jpg",
            "path": "https://ais-cf.tvnow.de/tvnow/movie/84453/",
            "filename": "episode-0002"
          },
          {
            "dimension": "2x",
            "src": "https://ais-cf.tvnow.de/tvnow/movie/84453/600x0/episode-0002.jpg",
            "path": "https://ais-cf.tvnow.de/tvnow/movie/84453/",
            "filename": "episode-0002"
          },
          {
            "dimension": "4x",
            "src": "https://ais-cf.tvnow.de/tvnow/movie/84453/1200x0/episode-0002.jpg",
            "path": "https://ais-cf.tvnow.de/tvnow/movie/84453/",
            "filename": "episode-0002"
          }
        ],
        "imagesHover": [
          {
            "dimension": "1x",
            "src": "https://ais-cf.tvnow.de/tvnow/movie/84453/300x0/episode-0002.jpg",
            "path": "https://ais-cf.tvnow.de/tvnow/movie/84453/",
            "filename": "episode-0002"
          },
          {
            "dimension": "2x",
            "src": "https://ais-cf.tvnow.de/tvnow/movie/84453/600x0/episode-0002.jpg",
            "path": "https://ais-cf.tvnow.de/tvnow/movie/84453/",
            "filename": "episode-0002"
          },
          {
            "dimension": "4x",
            "src": "https://ais-cf.tvnow.de/tvnow/movie/84453/1200x0/episode-0002.jpg",
            "path": "https://ais-cf.tvnow.de/tvnow/movie/84453/",
            "filename": "episode-0002"
          }
        ],
        "isPremium": true,
        "overlays": [
          "premium"
        ],
        "seoUrl": "hausenblas-staubsauger-vertreter-deluxe",
        "subheadline": "Episode 0002",
        "text": "Staffel 1, Folge 2 | Mo. 03.09.2018, 23:10 Uhr",
        "type": "show",
        "url": "/shows/hausenblas-staubsauger-vertreter-deluxe-2011/staffel-1/episode-2-episode-0002-84453",
        "videoId": 84453
      },
      {
        "buttons": [
          {
            "display": true,
            "formatId": 2011,
            "text": null,
            "type": "favorites"
          },
          {
            "display": true,
            "text": "Jetzt ansehen",
            "type": "play",
            "url": "/shows/hausenblas-staubsauger-vertreter-deluxe-2011/staffel-1/episode-3-episode-0003-85183"
          }
        ],
        "ecommerce": {
          "teaserFormatName": "Hausenblas - Staubsauger-Vertreter deluxe ",
          "teaserId": "show_episode_85183",
          "teaserName": "Hausenblas - Staubsauger-Vertreter deluxe  | Staffel 1 | Folge 3 | Episode 0003",
          "teaserPayType": "paid",
          "teaserType": "show_episode",
          "teaserGenre": "Real Life",
          "cluster": [
            "Lifestyle"
          ],
          "classification": [],
          "teaserSeason": "Staffel 1",
          "teaserEpisodeNumber": "Folge 3",
          "teaserEpisodeAirtime": "Di. 04.09.2018, 00:00 Uhr",
          "teaserEpisodeName": "Episode 0003"
        },
        "fsk": {
          "isVisible": false,
          "label": "ab 0",
          "minAge": 0
        },
        "headline": "Episode 0003",
        "id": 85183,
        "images": [
          {
            "dimension": "1x",
            "src": "https://ais-cf.tvnow.de/tvnow/movie/85183/300x0/episode-0003.jpg",
            "path": "https://ais-cf.tvnow.de/tvnow/movie/85183/",
            "filename": "episode-0003"
          },
          {
            "dimension": "2x",
            "src": "https://ais-cf.tvnow.de/tvnow/movie/85183/600x0/episode-0003.jpg",
            "path": "https://ais-cf.tvnow.de/tvnow/movie/85183/",
            "filename": "episode-0003"
          },
          {
            "dimension": "4x",
            "src": "https://ais-cf.tvnow.de/tvnow/movie/85183/1200x0/episode-0003.jpg",
            "path": "https://ais-cf.tvnow.de/tvnow/movie/85183/",
            "filename": "episode-0003"
          }
        ],
        "imagesHover": [
          {
            "dimension": "1x",
            "src": "https://ais-cf.tvnow.de/tvnow/movie/85183/300x0/episode-0003.jpg",
            "path": "https://ais-cf.tvnow.de/tvnow/movie/85183/",
            "filename": "episode-0003"
          },
          {
            "dimension": "2x",
            "src": "https://ais-cf.tvnow.de/tvnow/movie/85183/600x0/episode-0003.jpg",
            "path": "https://ais-cf.tvnow.de/tvnow/movie/85183/",
            "filename": "episode-0003"
          },
          {
            "dimension": "4x",
            "src": "https://ais-cf.tvnow.de/tvnow/movie/85183/1200x0/episode-0003.jpg",
            "path": "https://ais-cf.tvnow.de/tvnow/movie/85183/",
            "filename": "episode-0003"
          }
        ],
        "isPremium": true,
        "overlays": [
          "premium"
        ],
        "seoUrl": "hausenblas-staubsauger-vertreter-deluxe",
        "subheadline": "Episode 0003",
        "text": "Staffel 1, Folge 3 | Di. 04.09.2018, 00:00 Uhr",
        "type": "show",
        "url": "/shows/hausenblas-staubsauger-vertreter-deluxe-2011/staffel-1/episode-3-episode-0003-85183",
        "videoId": 85183
      },
      {
        "buttons": [
          {
            "display": true,
            "formatId": 2011,
            "text": null,
            "type": "favorites"
          },
          {
            "display": true,
            "text": "Jetzt ansehen",
            "type": "play",
            "url": "/shows/hausenblas-staubsauger-vertreter-deluxe-2011/staffel-1/episode-4-episode-0004-85867"
          }
        ],
        "ecommerce": {
          "teaserFormatName": "Hausenblas - Staubsauger-Vertreter deluxe ",
          "teaserId": "show_episode_85867",
          "teaserName": "Hausenblas - Staubsauger-Vertreter deluxe  | Staffel 1 | Folge 4 | Episode 0004",
          "teaserPayType": "paid",
          "teaserType": "show_episode",
          "teaserGenre": "Real Life",
          "cluster": [
            "Lifestyle"
          ],
          "classification": [],
          "teaserSeason": "Staffel 1",
          "teaserEpisodeNumber": "Folge 4",
          "teaserEpisodeAirtime": "Di. 04.09.2018, 00:55 Uhr",
          "teaserEpisodeName": "Episode 0004"
        },
        "fsk": {
          "isVisible": false,
          "label": "ab 0",
          "minAge": 0
        },
        "headline": "Episode 0004",
        "id": 85867,
        "images": [
          {
            "dimension": "1x",
            "src": "https://ais-cf.tvnow.de/tvnow/movie/85867/300x0/episode-0004.jpg",
            "path": "https://ais-cf.tvnow.de/tvnow/movie/85867/",
            "filename": "episode-0004"
          },
          {
            "dimension": "2x",
            "src": "https://ais-cf.tvnow.de/tvnow/movie/85867/600x0/episode-0004.jpg",
            "path": "https://ais-cf.tvnow.de/tvnow/movie/85867/",
            "filename": "episode-0004"
          },
          {
            "dimension": "4x",
            "src": "https://ais-cf.tvnow.de/tvnow/movie/85867/1200x0/episode-0004.jpg",
            "path": "https://ais-cf.tvnow.de/tvnow/movie/85867/",
            "filename": "episode-0004"
          }
        ],
        "imagesHover": [
          {
            "dimension": "1x",
            "src": "https://ais-cf.tvnow.de/tvnow/movie/85867/300x0/episode-0004.jpg",
            "path": "https://ais-cf.tvnow.de/tvnow/movie/85867/",
            "filename": "episode-0004"
          },
          {
            "dimension": "2x",
            "src": "https://ais-cf.tvnow.de/tvnow/movie/85867/600x0/episode-0004.jpg",
            "path": "https://ais-cf.tvnow.de/tvnow/movie/85867/",
            "filename": "episode-0004"
          },
          {
            "dimension": "4x",
            "src": "https://ais-cf.tvnow.de/tvnow/movie/85867/1200x0/episode-0004.jpg",
            "path": "https://ais-cf.tvnow.de/tvnow/movie/85867/",
            "filename": "episode-0004"
          }
        ],
        "isPremium": true,
        "overlays": [
          "premium"
        ],
        "seoUrl": "hausenblas-staubsauger-vertreter-deluxe",
        "subheadline": "Episode 0004",
        "text": "Staffel 1, Folge 4 | Di. 04.09.2018, 00:55 Uhr",
        "type": "show",
        "url": "/shows/hausenblas-staubsauger-vertreter-deluxe-2011/staffel-1/episode-4-episode-0004-85867",
        "videoId": 85867
      },
      {
        "buttons": [
          {
            "display": true,
            "formatId": 2011,
            "text": null,
            "type": "favorites"
          },
          {
            "display": true,
            "text": "Jetzt ansehen",
            "type": "play",
            "url": "/shows/hausenblas-staubsauger-vertreter-deluxe-2011/staffel-1/episode-5-episode-0005-86585"
          }
        ],
        "ecommerce": {
          "teaserFormatName": "Hausenblas - Staubsauger-Vertreter deluxe ",
          "teaserId": "show_episode_86585",
          "teaserName": "Hausenblas - Staubsauger-Vertreter deluxe  | Staffel 1 | Folge 5 | Episode 0005",
          "teaserPayType": "paid",
          "teaserType": "show_episode",
          "teaserGenre": "Real Life",
          "cluster": [
            "Lifestyle"
          ],
          "classification": [],
          "teaserSeason": "Staffel 1",
          "teaserEpisodeNumber": "Folge 5",
          "teaserEpisodeAirtime": "Di. 04.09.2018, 01:50 Uhr",
          "teaserEpisodeName": "Episode 0005"
        },
        "fsk": {
          "isVisible": false,
          "label": "ab 0",
          "minAge": 0
        },
        "headline": "Episode 0005",
        "id": 86585,
        "images": [
          {
            "dimension": "1x",
            "src": "https://ais-cf.tvnow.de/tvnow/movie/86585/300x0/episode-0005.jpg",
            "path": "https://ais-cf.tvnow.de/tvnow/movie/86585/",
            "filename": "episode-0005"
          },
          {
            "dimension": "2x",
            "src": "https://ais-cf.tvnow.de/tvnow/movie/86585/600x0/episode-0005.jpg",
            "path": "https://ais-cf.tvnow.de/tvnow/movie/86585/",
            "filename": "episode-0005"
          },
          {
            "dimension": "4x",
            "src": "https://ais-cf.tvnow.de/tvnow/movie/86585/1200x0/episode-0005.jpg",
            "path": "https://ais-cf.tvnow.de/tvnow/movie/86585/",
            "filename": "episode-0005"
          }
        ],
        "imagesHover": [
          {
            "dimension": "1x",
            "src": "https://ais-cf.tvnow.de/tvnow/movie/86585/300x0/episode-0005.jpg",
            "path": "https://ais-cf.tvnow.de/tvnow/movie/86585/",
            "filename": "episode-0005"
          },
          {
            "dimension": "2x",
            "src": "https://ais-cf.tvnow.de/tvnow/movie/86585/600x0/episode-0005.jpg",
            "path": "https://ais-cf.tvnow.de/tvnow/movie/86585/",
            "filename": "episode-0005"
          },
          {
            "dimension": "4x",
            "src": "https://ais-cf.tvnow.de/tvnow/movie/86585/1200x0/episode-0005.jpg",
            "path": "https://ais-cf.tvnow.de/tvnow/movie/86585/",
            "filename": "episode-0005"
          }
        ],
        "isPremium": true,
        "overlays": [
          "premium"
        ],
        "seoUrl": "hausenblas-staubsauger-vertreter-deluxe",
        "subheadline": "Episode 0005",
        "text": "Staffel 1, Folge 5 | Di. 04.09.2018, 01:50 Uhr",
        "type": "show",
        "url": "/shows/hausenblas-staubsauger-vertreter-deluxe-2011/staffel-1/episode-5-episode-0005-86585",
        "videoId": 86585
      },
      {
        "buttons": [
          {
            "display": true,
            "formatId": 2011,
            "text": null,
            "type": "favorites"
          },
          {
            "display": true,
            "text": "Jetzt ansehen",
            "type": "play",
            "url": "/shows/hausenblas-staubsauger-vertreter-deluxe-2011/staffel-1/episode-6-episode-0006-87287"
          }
        ],
        "ecommerce": {
          "teaserFormatName": "Hausenblas - Staubsauger-Vertreter deluxe ",
          "teaserId": "show_episode_87287",
          "teaserName": "Hausenblas - Staubsauger-Vertreter deluxe  | Staffel 1 | Folge 6 | Episode 0006",
          "teaserPayType": "paid",
          "teaserType": "show_episode",
          "teaserGenre": "Real Life",
          "cluster": [
            "Lifestyle"
          ],
          "classification": [],
          "teaserSeason": "Staffel 1",
          "teaserEpisodeNumber": "Folge 6",
          "teaserEpisodeAirtime": "Di. 04.09.2018, 02:40 Uhr",
          "teaserEpisodeName": "Episode 0006"
        },
        "fsk": {
          "isVisible": false,
          "label": "ab 0",
          "minAge": 0
        },
        "headline": "Episode 0006",
        "id": 87287,
        "images": [
          {
            "dimension": "1x",
            "src": "https://ais-cf.tvnow.de/tvnow/movie/87287/300x0/episode-0006.jpg",
            "path": "https://ais-cf.tvnow.de/tvnow/movie/87287/",
            "filename": "episode-0006"
          },
          {
            "dimension": "2x",
            "src": "https://ais-cf.tvnow.de/tvnow/movie/87287/600x0/episode-0006.jpg",
            "path": "https://ais-cf.tvnow.de/tvnow/movie/87287/",
            "filename": "episode-0006"
          },
          {
            "dimension": "4x",
            "src": "https://ais-cf.tvnow.de/tvnow/movie/87287/1200x0/episode-0006.jpg",
            "path": "https://ais-cf.tvnow.de/tvnow/movie/87287/",
            "filename": "episode-0006"
          }
        ],
        "imagesHover": [
          {
            "dimension": "1x",
            "src": "https://ais-cf.tvnow.de/tvnow/movie/87287/300x0/episode-0006.jpg",
            "path": "https://ais-cf.tvnow.de/tvnow/movie/87287/",
            "filename": "episode-0006"
          },
          {
            "dimension": "2x",
            "src": "https://ais-cf.tvnow.de/tvnow/movie/87287/600x0/episode-0006.jpg",
            "path": "https://ais-cf.tvnow.de/tvnow/movie/87287/",
            "filename": "episode-0006"
          },
          {
            "dimension": "4x",
            "src": "https://ais-cf.tvnow.de/tvnow/movie/87287/1200x0/episode-0006.jpg",
            "path": "https://ais-cf.tvnow.de/tvnow/movie/87287/",
            "filename": "episode-0006"
          }
        ],
        "isPremium": true,
        "overlays": [
          "premium"
        ],
        "seoUrl": "hausenblas-staubsauger-vertreter-deluxe",
        "subheadline": "Episode 0006",
        "text": "Staffel 1, Folge 6 | Di. 04.09.2018, 02:40 Uhr",
        "type": "show",
        "url": "/shows/hausenblas-staubsauger-vertreter-deluxe-2011/staffel-1/episode-6-episode-0006-87287",
        "videoId": 87287
      }
    ],
    "format_navigation": {
      "season": 1
    },
    "navigationType": "season"
  }
]