[
  {
    "ecommerce": {
      "rowCategory": "small_teaser",
      "rowId": "na",
      "rowName": "Staffel 2"
    },
    "id": null,
    "label": null,
    "moduleLayout": "format_episode",
    "moduleUrl": "/module/teaserrow/format/episode/18042",
    "type": "teaserrow",
    "items": [
      {
        "buttons": [
          {
            "display": true,
            "formatId": 18042,
            "text": null,
            "type": "favorites"
          },
          {
            "display": true,
            "text": "Jetzt ansehen",
            "type": "play",
            "url": "/shows/super-toy-club-18042/staffel-2/episode-16-folge-16-3240559"
          }
        ],
        "ecommerce": {
          "teaserFormatName": "Super Toy Club",
          "teaserId": "show_episode_3240559",
          "teaserName": "Super Toy Club | Staffel 2 | Folge 16 | Folge 16",
          "teaserPayType": "paid",
          "teaserType": "show_episode",
          "teaserGenre": "Kinder",
          "cluster": [
            "KIDS 6 bis 10 Jahre",
            "KIDS Jungs",
            "KIDS Mädchen",
            "Kids"
          ],
          "classification": [],
          "teaserSeason": "Staffel 2",
          "teaserEpisodeNumber": "Folge 16",
          "teaserEpisodeAirtime": "Sa. 05.09.2020, 08:00 Uhr",
          "teaserEpisodeName": "Folge 16"
        },
        "fsk": {
          "isVisible": false,
          "label": "ab 0",
          "minAge": 0
        },
        "headline": "Folge 16",
        "id": 3240559,
        "images": [
          {
            "dimension": "1x",
            "src": "https://ais-cf.tvnow.de/tvnow/movie/3240559/300x0/folge-16.jpg",
            "path": "https://ais-cf.tvnow.de/tvnow/movie/3240559/",
            "filename": "folge-16"
          },
          {
            "dimension": "2x",
            "src": "https://ais-cf.tvnow.de/tvnow/movie/3240559/600x0/folge-16.jpg",
            "path": "https://ais-cf.tvnow.de/tvnow/movie/3240559/",
            "filename": "folge-16"
          },
          {
            "dimension": "4x",
            "src": "https://ais-cf.tvnow.de/tvnow/movie/3240559/1200x0/folge-16.jpg",
            "path": "https://ais-cf.tvnow.de/tvnow/movie/3240559/",
            "filename": "folge-16"
          }
        ],
        "imagesHover": [
          {
            "dimension": "1x",
            "src": "https://ais-cf.tvnow.de/tvnow/movie/3240559/300x0/folge-16.jpg",
            "path": "https://ais-cf.tvnow.de/tvnow/movie/3240559/",
            "filename": "folge-16"
          },
          {
            "dimension": "2x",
            "src": "https://ais-cf.tvnow.de/tvnow/movie/3240559/600x0/folge-16.jpg",
            "path": "https://ais-cf.tvnow.de/tvnow/movie/3240559/",
            "filename": "folge-16"
          },
          {
            "dimension": "4x",
            "src": "https://ais-cf.tvnow.de/tvnow/movie/3240559/1200x0/folge-16.jpg",
            "path": "https://ais-cf.tvnow.de/tvnow/movie/3240559/",
            "filename": "folge-16"
          }
        ],
        "isPremium": true,
        "overlays": [
          "premium"
        ],
        "seoUrl": "super-toy-club",
        "subheadline": "Folge 16",
        "text": "Staffel 2, Folge 16 | Sa. 05.09.2020, 08:00 Uhr",
        "type": "show",
        "url": "/shows/super-toy-club-18042/staffel-2/episode-16-folge-16-3240559",
        "videoId": 3240559
      },
      {
        "buttons": [
          {
            "display": true,
            "formatId": 18042,
            "text": null,
            "type": "favorites"
          },
          {
            "display": true,
            "text": "Jetzt ansehen",
            "type": "play",
            "url": "/shows/super-toy-club-18042/staffel-2/episode-17-folge-17-3240574"
          }
        ],
        "ecommerce": {
          "teaserFormatName": "Super Toy Club",
          "teaserId": "show_episode_3240574",
          "teaserName": "Super Toy Club | Staffel 2 | Folge 17 | Folge 17",
          "teaserPayType": "paid",
          "teaserType": "show_episode",
          "teaserGenre": "Kinder",
          "cluster": [
            "KIDS 6 bis 10 Jahre",
            "KIDS Jungs",
            "KIDS Mädchen",
            "Kids"
          ],
          "classification": [],
          "teaserSeason": "Staffel 2",
          "teaserEpisodeNumber": "Folge 17",
          "teaserEpisodeAirtime": "So. 06.09.2020, 08:00 Uhr",
          "teaserEpisodeName": "Folge 17"
        },
        "fsk": {
          "isVisible": false,
          "label": "ab 0",
          "minAge": 0
        },
        "headline": "Folge 17",
        "id": 3240574,
        "images": [
          {
            "dimension": "1x",
            "src": "https://ais-cf.tvnow.de/tvnow/movie/3240574/300x0/folge-17.jpg",
            "path": "https://ais-cf.tvnow.de/tvnow/movie/3240574/",
            "filename": "folge-17"
          },
          {
            "dimension": "2x",
            "src": "https://ais-cf.tvnow.de/tvnow/movie/3240574/600x0/folge-17.jpg",
            "path": "https://ais-cf.tvnow.de/tvnow/movie/3240574/",
            "filename": "folge-17"
          },
          {
            "dimension": "4x",
            "src": "https://ais-cf.tvnow.de/tvnow/movie/3240574/1200x0/folge-17.jpg",
            "path": "https://ais-cf.tvnow.de/tvnow/movie/3240574/",
            "filename": "folge-17"
          }
        ],
        "imagesHover": [
          {
            "dimension": "1x",
            "src": "https://ais-cf.tvnow.de/tvnow/movie/3240574/300x0/folge-17.jpg",
            "path": "https://ais-cf.tvnow.de/tvnow/movie/3240574/",
            "filename": "folge-17"
          },
          {
            "dimension": "2x",
            "src": "https://ais-cf.tvnow.de/tvnow/movie/3240574/600x0/folge-17.jpg",
            "path": "https://ais-cf.tvnow.de/tvnow/movie/3240574/",
            "filename": "folge-17"
          },
          {
            "dimension": "4x",
            "src": "https://ais-cf.tvnow.de/tvnow/movie/3240574/1200x0/folge-17.jpg",
            "path": "https://ais-cf.tvnow.de/tvnow/movie/3240574/",
            "filename": "folge-17"
          }
        ],
        "isPremium": true,
        "overlays": [
          "premium"
        ],
        "seoUrl": "super-toy-club",
        "subheadline": "Folge 17",
        "text": "Staffel 2, Folge 17 | So. 06.09.2020, 08:00 Uhr",
        "type": "show",
        "url": "/shows/super-toy-club-18042/staffel-2/episode-17-folge-17-3240574",
        "videoId": 3240574
      },
      {
        "buttons": [
          {
            "display": true,
            "formatId": 18042,
            "text": null,
            "type": "favorites"
          },
          {
            "display": true,
            "text": "Jetzt ansehen",
            "type": "play",
            "url": "/shows/super-toy-club-18042/staffel-2/episode-18-folge-18-3240550"
          }
        ],
        "ecommerce": {
          "teaserFormatName": "Super Toy Club",
          "teaserId": "show_episode_3240550",
          "teaserName": "Super Toy Club | Staffel 2 | Folge 18 | Folge 18",
          "teaserPayType": "paid",
          "teaserType": "show_episode",
          "teaserGenre": "Kinder",
          "cluster": [
            "KIDS 6 bis 10 Jahre",
            "KIDS Jungs",
            "KIDS Mädchen",
            "Kids"
          ],
          "classification": [],
          "teaserSeason": "Staffel 2",
          "teaserEpisodeNumber": "Folge 18",
          "teaserEpisodeAirtime": "Sa. 25.04.2020, 09:00 Uhr",
          "teaserEpisodeName": "Folge 18"
        },
        "fsk": {
          "isVisible": false,
          "label": "ab 0",
          "minAge": 0
        },
        "headline": "Folge 18",
        "id": 3240550,
        "images": [
          {
            "dimension": "1x",
            "src": "https://ais-cf.tvnow.de/tvnow/movie/3240550/300x0/folge-18.jpg",
            "path": "https://ais-cf.tvnow.de/tvnow/movie/3240550/",
            "filename": "folge-18"
          },
          {
            "dimension": "2x",
            "src": "https://ais-cf.tvnow.de/tvnow/movie/3240550/600x0/folge-18.jpg",
            "path": "https://ais-cf.tvnow.de/tvnow/movie/3240550/",
            "filename": "folge-18"
          },
          {
            "dimension": "4x",
            "src": "https://ais-cf.tvnow.de/tvnow/movie/3240550/1200x0/folge-18.jpg",
            "path": "https://ais-cf.tvnow.de/tvnow/movie/3240550/",
            "filename": "folge-18"
          }
        ],
        "imagesHover": [
          {
            "dimension": "1x",
            "src": "https://ais-cf.tvnow.de/tvnow/movie/3240550/300x0/folge-18.jpg",
            "path": "https://ais-cf.tvnow.de/tvnow/movie/3240550/",
            "filename": "folge-18"
          },
          {
            "dimension": "2x",
            "src": "https://ais-cf.tvnow.de/tvnow/movie/3240550/600x0/folge-18.jpg",
            "path": "https://ais-cf.tvnow.de/tvnow/movie/3240550/",
            "filename": "folge-18"
          },
          {
            "dimension": "4x",
            "src": "https://ais-cf.tvnow.de/tvnow/movie/3240550/1200x0/folge-18.jpg",
            "path": "https://ais-cf.tvnow.de/tvnow/movie/3240550/",
            "filename": "folge-18"
          }
        ],
        "isPremium": true,
        "overlays": [
          "premium"
        ],
        "seoUrl": "super-toy-club",
        "subheadline": "Folge 18",
        "text": "Staffel 2, Folge 18 | Sa. 25.04.2020, 09:00 Uhr",
        "type": "show",
        "url": "/shows/super-toy-club-18042/staffel-2/episode-18-folge-18-3240550",
        "videoId": 3240550
      },
      {
        "buttons": [
          {
            "display": true,
            "formatId": 18042,
            "text": null,
            "type": "favorites"
          },
          {
            "display": true,
            "text": "Jetzt ansehen",
            "type": "play",
            "url": "/shows/super-toy-club-18042/staffel-2/episode-19-best-friends-vs-hollager-jungs-3240572"
          }
        ],
        "ecommerce": {
          "teaserFormatName": "Super Toy Club",
          "teaserId": "show_episode_3240572",
          "teaserName": "Super Toy Club | Staffel 2 | Folge 19 | \"Best Friends\" vs. \"Hollager Jungs\" ",
          "teaserPayType": "paid",
          "teaserType": "show_episode",
          "teaserGenre": "Kinder",
          "cluster": [
            "KIDS 6 bis 10 Jahre",
            "KIDS Jungs",
            "KIDS Mädchen",
            "Kids"
          ],
          "classification": [],
          "teaserSeason": "Staffel 2",
          "teaserEpisodeNumber": "Folge 19",
          "teaserEpisodeAirtime": "So. 13.09.2020, 08:00 Uhr",
          "teaserEpisodeName": "\"Best Friends\" vs. \"Hollager Jungs\" "
        },
        "fsk": {
          "isVisible": false,
          "label": "ab 0",
          "minAge": 0
        },
        "headline": "\"Best Friends\" vs. \"Hollager Jungs\" ",
        "id": 3240572,
        "images": [
          {
            "dimension": "1x",
            "src": "https://ais-cf.tvnow.de/tvnow/movie/3240572/300x0/best-friends-vs-hollager-jungs.jpg",
            "path": "https://ais-cf.tvnow.de/tvnow/movie/3240572/",
            "filename": "best-friends-vs-hollager-jungs"
          },
          {
            "dimension": "2x",
            "src": "https://ais-cf.tvnow.de/tvnow/movie/3240572/600x0/best-friends-vs-hollager-jungs.jpg",
            "path": "https://ais-cf.tvnow.de/tvnow/movie/3240572/",
            "filename": "best-friends-vs-hollager-jungs"
          },
          {
            "dimension": "4x",
            "src": "https://ais-cf.tvnow.de/tvnow/movie/3240572/1200x0/best-friends-vs-hollager-jungs.jpg",
            "path": "https://ais-cf.tvnow.de/tvnow/movie/3240572/",
            "filename": "best-friends-vs-hollager-jungs"
          }
        ],
        "imagesHover": [
          {
            "dimension": "1x",
            "src": "https://ais-cf.tvnow.de/tvnow/movie/3240572/300x0/best-friends-vs-hollager-jungs.jpg",
            "path": "https://ais-cf.tvnow.de/tvnow/movie/3240572/",
            "filename": "best-friends-vs-hollager-jungs"
          },
          {
            "dimension": "2x",
            "src": "https://ais-cf.tvnow.de/tvnow/movie/3240572/600x0/best-friends-vs-hollager-jungs.jpg",
            "path": "https://ais-cf.tvnow.de/tvnow/movie/3240572/",
            "filename": "best-friends-vs-hollager-jungs"
          },
          {
            "dimension": "4x",
            "src": "https://ais-cf.tvnow.de/tvnow/movie/3240572/1200x0/best-friends-vs-hollager-jungs.jpg",
            "path": "https://ais-cf.tvnow.de/tvnow/movie/3240572/",
            "filename": "best-friends-vs-hollager-jungs"
          }
        ],
        "isPremium": true,
        "overlays": [
          "premium"
        ],
        "seoUrl": "super-toy-club",
        "subheadline": "\"Best Friends\" vs. \"Hollager Jungs\" ",
        "text": "Staffel 2, Folge 19 | So. 13.09.2020, 08:00 Uhr",
        "type": "show",
        "url": "/shows/super-toy-club-18042/staffel-2/episode-19-best-friends-vs-hollager-jungs-3240572",
        "videoId": 3240572
      },
      {
        "buttons": [
          {
            "display": true,
            "formatId": 18042,
            "text": null,
            "type": "favorites"
          },
          {
            "display": true,
            "text": "Jetzt ansehen",
            "type": "play",
            "url": "/shows/super-toy-club-18042/staffel-2/episode-20-folge-20-3240554"
          }
        ],
        "ecommerce": {
          "teaserFormatName": "Super Toy Club",
          "teaserId": "show_episode_3240554",
          "teaserName": "Super Toy Club | Staffel 2 | Folge 20 | Folge 20",
          "teaserPayType": "paid",
          "teaserType": "show_episode",
          "teaserGenre": "Kinder",
          "cluster": [
            "KIDS 6 bis 10 Jahre",
            "KIDS Jungs",
            "KIDS Mädchen",
            "Kids"
          ],
          "classification": [],
          "teaserSeason": "Staffel 2",
          "teaserEpisodeNumber": "Folge 20",
          "teaserEpisodeAirtime": "Sa. 19.09.2020, 08:00 Uhr",
          "teaserEpisodeName": "Folge 20"
        },
        "fsk": {
          "isVisible": false,
          "label": "ab 0",
          "minAge": 0
        },
        "headline": "Folge 20",
        "id": 3240554,
        "images": [
          {
            "dimension": "1x",
            "src": "https://ais-cf.tvnow.de/tvnow/movie/3240554/300x0/folge-20.jpg",
            "path": "https://ais-cf.tvnow.de/tvnow/movie/3240554/",
            "filename": "folge-20"
          },
          {
            "dimension": "2x",
            "src": "https://ais-cf.tvnow.de/tvnow/movie/3240554/600x0/folge-20.jpg",
            "path": "https://ais-cf.tvnow.de/tvnow/movie/3240554/",
            "filename": "folge-20"
          },
          {
            "dimension": "4x",
            "src": "https://ais-cf.tvnow.de/tvnow/movie/3240554/1200x0/folge-20.jpg",
            "path": "https://ais-cf.tvnow.de/tvnow/movie/3240554/",
            "filename": "folge-20"
          }
        ],
        "imagesHover": [
          {
            "dimension": "1x",
            "src": "https://ais-cf.tvnow.de/tvnow/movie/3240554/300x0/folge-20.jpg",
            "path": "https://ais-cf.tvnow.de/tvnow/movie/3240554/",
            "filename": "folge-20"
          },
          {
            "dimension": "2x",
            "src": "https://ais-cf.tvnow.de/tvnow/movie/3240554/600x0/folge-20.jpg",
            "path": "https://ais-cf.tvnow.de/tvnow/movie/3240554/",
            "filename": "folge-20"
          },
          {
            "dimension": "4x",
            "src": "https://ais-cf.tvnow.de/tvnow/movie/3240554/1200x0/folge-20.jpg",
            "path": "https://ais-cf.tvnow.de/tvnow/movie/3240554/",
            "filename": "folge-20"
          }
        ],
        "isPremium": true,
        "overlays": [
          "premium"
        ],
        "seoUrl": "super-toy-club",
        "subheadline": "Folge 20",
        "text": "Staffel 2, Folge 20 | Sa. 19.09.2020, 08:00 Uhr",
        "type": "show",
        "url": "/shows/super-toy-club-18042/staffel-2/episode-20-folge-20-3240554",
        "videoId": 3240554
      },
      {
        "buttons": [
          {
            "display": true,
            "formatId": 18042,
            "text": null,
            "type": "favorites"
          },
          {
            "display": true,
            "text": "Jetzt ansehen",
            "type": "play",
            "url": "/shows/super-toy-club-18042/staffel-2/episode-21-folge-21-3240555"
          }
        ],
        "ecommerce": {
          "teaserFormatName": "Super Toy Club",
          "teaserId": "show_episode_3240555",
          "teaserName": "Super Toy Club | Staffel 2 | Folge 21 | Folge 21",
          "teaserPayType": "paid",
          "teaserType": "show_episode",
          "teaserGenre": "Kinder",
          "cluster": [
            "KIDS 6 bis 10 Jahre",
            "KIDS Jungs",
            "KIDS Mädchen",
            "Kids"
          ],
          "classification": [],
          "teaserSeason": "Staffel 2",
          "teaserEpisodeNumber": "Folge 21",
          "teaserEpisodeAirtime": "So. 20.09.2020, 08:00 Uhr",
          "teaserEpisodeName": "Folge 21"
        },
        "fsk": {
          "isVisible": false,
          "label": "ab 0",
          "minAge": 0
        },
        "headline": "Folge 21",
        "id": 3240555,
        "images": [
          {
            "dimension": "1x",
            "src": "https://ais-cf.tvnow.de/tvnow/movie/3240555/300x0/folge-21.jpg",
            "path": "https://ais-cf.tvnow.de/tvnow/movie/3240555/",
            "filename": "folge-21"
          },
          {
            "dimension": "2x",
            "src": "https://ais-cf.tvnow.de/tvnow/movie/3240555/600x0/folge-21.jpg",
            "path": "https://ais-cf.tvnow.de/tvnow/movie/3240555/",
            "filename": "folge-21"
          },
          {
            "dimension": "4x",
            "src": "https://ais-cf.tvnow.de/tvnow/movie/3240555/1200x0/folge-21.jpg",
            "path": "https://ais-cf.tvnow.de/tvnow/movie/3240555/",
            "filename": "folge-21"
          }
        ],
        "imagesHover": [
          {
            "dimension": "1x",
            "src": "https://ais-cf.tvnow.de/tvnow/movie/3240555/300x0/folge-21.jpg",
            "path": "https://ais-cf.tvnow.de/tvnow/movie/3240555/",
            "filename": "folge-21"
          },
          {
            "dimension": "2x",
            "src": "https://ais-cf.tvnow.de/tvnow/movie/3240555/600x0/folge-21.jpg",
            "path": "https://ais-cf.tvnow.de/tvnow/movie/3240555/",
            "filename": "folge-21"
          },
          {
            "dimension": "4x",
            "src": "https://ais-cf.tvnow.de/tvnow/movie/3240555/1200x0/folge-21.jpg",
            "path": "https://ais-cf.tvnow.de/tvnow/movie/3240555/",
            "filename": "folge-21"
          }
        ],
        "isPremium": true,
        "overlays": [
          "premium"
        ],
        "seoUrl": "super-toy-club",
        "subheadline": "Folge 21",
        "text": "Staffel 2, Folge 21 | So. 20.09.2020, 08:00 Uhr",
        "type": "show",
        "url": "/shows/super-toy-club-18042/staffel-2/episode-21-folge-21-3240555",
        "videoId": 3240555
      },
      {
        "buttons": [
          {
            "display": true,
            "formatId": 18042,
            "text": null,
            "type": "favorites"
          },
          {
            "display": true,
            "text": "Jetzt ansehen",
            "type": "play",
            "url": "/shows/super-toy-club-18042/staffel-2/episode-22-folge-22-3240548"
          }
        ],
        "ecommerce": {
          "teaserFormatName": "Super Toy Club",
          "teaserId": "show_episode_3240548",
          "teaserName": "Super Toy Club | Staffel 2 | Folge 22 | Folge 22",
          "teaserPayType": "paid",
          "teaserType": "show_episode",
          "teaserGenre": "Kinder",
          "cluster": [
            "KIDS 6 bis 10 Jahre",
            "KIDS Jungs",
            "KIDS Mädchen",
            "Kids"
          ],
          "classification": [],
          "teaserSeason": "Staffel 2",
          "teaserEpisodeNumber": "Folge 22",
          "teaserEpisodeAirtime": "Sa. 26.09.2020, 08:00 Uhr",
          "teaserEpisodeName": "Folge 22"
        },
        "fsk": {
          "isVisible": false,
          "label": "ab 0",
          "minAge": 0
        },
        "headline": "Folge 22",
        "id": 3240548,
        "images": [
          {
            "dimension": "1x",
            "src": "https://ais-cf.tvnow.de/tvnow/movie/3240548/300x0/folge-22.jpg",
            "path": "https://ais-cf.tvnow.de/tvnow/movie/3240548/",
            "filename": "folge-22"
          },
          {
            "dimension": "2x",
            "src": "https://ais-cf.tvnow.de/tvnow/movie/3240548/600x0/folge-22.jpg",
            "path": "https://ais-cf.tvnow.de/tvnow/movie/3240548/",
            "filename": "folge-22"
          },
          {
            "dimension": "4x",
            "src": "https://ais-cf.tvnow.de/tvnow/movie/3240548/1200x0/folge-22.jpg",
            "path": "https://ais-cf.tvnow.de/tvnow/movie/3240548/",
            "filename": "folge-22"
          }
        ],
        "imagesHover": [
          {
            "dimension": "1x",
            "src": "https://ais-cf.tvnow.de/tvnow/movie/3240548/300x0/folge-22.jpg",
            "path": "https://ais-cf.tvnow.de/tvnow/movie/3240548/",
            "filename": "folge-22"
          },
          {
            "dimension": "2x",
            "src": "https://ais-cf.tvnow.de/tvnow/movie/3240548/600x0/folge-22.jpg",
            "path": "https://ais-cf.tvnow.de/tvnow/movie/3240548/",
            "filename": "folge-22"
          },
          {
            "dimension": "4x",
            "src": "https://ais-cf.tvnow.de/tvnow/movie/3240548/1200x0/folge-22.jpg",
            "path": "https://ais-cf.tvnow.de/tvnow/movie/3240548/",
            "filename": "folge-22"
          }
        ],
        "isPremium": true,
        "overlays": [
          "premium"
        ],
        "seoUrl": "super-toy-club",
        "subheadline": "Folge 22",
        "text": "Staffel 2, Folge 22 | Sa. 26.09.2020, 08:00 Uhr",
        "type": "show",
        "url": "/shows/super-toy-club-18042/staffel-2/episode-22-folge-22-3240548",
        "videoId": 3240548
      },
      {
        "buttons": [
          {
            "display": true,
            "formatId": 18042,
            "text": null,
            "type": "favorites"
          },
          {
            "display": true,
            "text": "Jetzt ansehen",
            "type": "play",
            "url": "/shows/super-toy-club-18042/staffel-2/episode-23-folge-23-3240549"
          }
        ],
        "ecommerce": {
          "teaserFormatName": "Super Toy Club",
          "teaserId": "show_episode_3240549",
          "teaserName": "Super Toy Club | Staffel 2 | Folge 23 | Folge 23",
          "teaserPayType": "paid",
          "teaserType": "show_episode",
          "teaserGenre": "Kinder",
          "cluster": [
            "KIDS 6 bis 10 Jahre",
            "KIDS Jungs",
            "KIDS Mädchen",
            "Kids"
          ],
          "classification": [],
          "teaserSeason": "Staffel 2",
          "teaserEpisodeNumber": "Folge 23",
          "teaserEpisodeAirtime": "So. 27.09.2020, 08:00 Uhr",
          "teaserEpisodeName": "Folge 23"
        },
        "fsk": {
          "isVisible": false,
          "label": "ab 0",
          "minAge": 0
        },
        "headline": "Folge 23",
        "id": 3240549,
        "images": [
          {
            "dimension": "1x",
            "src": "https://ais-cf.tvnow.de/tvnow/movie/3240549/300x0/folge-23.jpg",
            "path": "https://ais-cf.tvnow.de/tvnow/movie/3240549/",
            "filename": "folge-23"
          },
          {
            "dimension": "2x",
            "src": "https://ais-cf.tvnow.de/tvnow/movie/3240549/600x0/folge-23.jpg",
            "path": "https://ais-cf.tvnow.de/tvnow/movie/3240549/",
            "filename": "folge-23"
          },
          {
            "dimension": "4x",
            "src": "https://ais-cf.tvnow.de/tvnow/movie/3240549/1200x0/folge-23.jpg",
            "path": "https://ais-cf.tvnow.de/tvnow/movie/3240549/",
            "filename": "folge-23"
          }
        ],
        "imagesHover": [
          {
            "dimension": "1x",
            "src": "https://ais-cf.tvnow.de/tvnow/movie/3240549/300x0/folge-23.jpg",
            "path": "https://ais-cf.tvnow.de/tvnow/movie/3240549/",
            "filename": "folge-23"
          },
          {
            "dimension": "2x",
            "src": "https://ais-cf.tvnow.de/tvnow/movie/3240549/600x0/folge-23.jpg",
            "path": "https://ais-cf.tvnow.de/tvnow/movie/3240549/",
            "filename": "folge-23"
          },
          {
            "dimension": "4x",
            "src": "https://ais-cf.tvnow.de/tvnow/movie/3240549/1200x0/folge-23.jpg",
            "path": "https://ais-cf.tvnow.de/tvnow/movie/3240549/",
            "filename": "folge-23"
          }
        ],
        "isPremium": true,
        "overlays": [
          "premium"
        ],
        "seoUrl": "super-toy-club",
        "subheadline": "Folge 23",
        "text": "Staffel 2, Folge 23 | So. 27.09.2020, 08:00 Uhr",
        "type": "show",
        "url": "/shows/super-toy-club-18042/staffel-2/episode-23-folge-23-3240549",
        "videoId": 3240549
      },
      {
        "buttons": [
          {
            "display": true,
            "formatId": 18042,
            "text": null,
            "type": "favorites"
          },
          {
            "display": true,
            "text": "Jetzt ansehen",
            "type": "play",
            "url": "/shows/super-toy-club-18042/staffel-2/episode-24-folge-24-3240540"
          }
        ],
        "ecommerce": {
          "teaserFormatName": "Super Toy Club",
          "teaserId": "show_episode_3240540",
          "teaserName": "Super Toy Club | Staffel 2 | Folge 24 | Folge 24",
          "teaserPayType": "paid",
          "teaserType": "show_episode",
          "teaserGenre": "Kinder",
          "cluster": [
            "KIDS 6 bis 10 Jahre",
            "KIDS Jungs",
            "KIDS Mädchen",
            "Kids"
          ],
          "classification": [],
          "teaserSeason": "Staffel 2",
          "teaserEpisodeNumber": "Folge 24",
          "teaserEpisodeAirtime": "Sa. 03.10.2020, 08:00 Uhr",
          "teaserEpisodeName": "Folge 24"
        },
        "fsk": {
          "isVisible": false,
          "label": "ab 0",
          "minAge": 0
        },
        "headline": "Folge 24",
        "id": 3240540,
        "images": [
          {
            "dimension": "1x",
            "src": "https://ais-cf.tvnow.de/tvnow/movie/3240540/300x0/folge-24.jpg",
            "path": "https://ais-cf.tvnow.de/tvnow/movie/3240540/",
            "filename": "folge-24"
          },
          {
            "dimension": "2x",
            "src": "https://ais-cf.tvnow.de/tvnow/movie/3240540/600x0/folge-24.jpg",
            "path": "https://ais-cf.tvnow.de/tvnow/movie/3240540/",
            "filename": "folge-24"
          },
          {
            "dimension": "4x",
            "src": "https://ais-cf.tvnow.de/tvnow/movie/3240540/1200x0/folge-24.jpg",
            "path": "https://ais-cf.tvnow.de/tvnow/movie/3240540/",
            "filename": "folge-24"
          }
        ],
        "imagesHover": [
          {
            "dimension": "1x",
            "src": "https://ais-cf.tvnow.de/tvnow/movie/3240540/300x0/folge-24.jpg",
            "path": "https://ais-cf.tvnow.de/tvnow/movie/3240540/",
            "filename": "folge-24"
          },
          {
            "dimension": "2x",
            "src": "https://ais-cf.tvnow.de/tvnow/movie/3240540/600x0/folge-24.jpg",
            "path": "https://ais-cf.tvnow.de/tvnow/movie/3240540/",
            "filename": "folge-24"
          },
          {
            "dimension": "4x",
            "src": "https://ais-cf.tvnow.de/tvnow/movie/3240540/1200x0/folge-24.jpg",
            "path": "https://ais-cf.tvnow.de/tvnow/movie/3240540/",
            "filename": "folge-24"
          }
        ],
        "isPremium": true,
        "overlays": [
          "premium"
        ],
        "seoUrl": "super-toy-club",
        "subheadline": "Folge 24",
        "text": "Staffel 2, Folge 24 | Sa. 03.10.2020, 08:00 Uhr",
        "type": "show",
        "url": "/shows/super-toy-club-18042/staffel-2/episode-24-folge-24-3240540",
        "videoId": 3240540
      },
      {
        "buttons": [
          {
            "display": true,
            "formatId": 18042,
            "text": null,
            "type": "favorites"
          },
          {
            "display": true,
            "text": "Jetzt ansehen",
            "type": "play",
            "url": "/shows/super-toy-club-18042/staffel-2/episode-25-folge-25-3240553"
          }
        ],
        "ecommerce": {
          "teaserFormatName": "Super Toy Club",
          "teaserId": "show_episode_3240553",
          "teaserName": "Super Toy Club | Staffel 2 | Folge 25 | Folge 25",
          "teaserPayType": "paid",
          "teaserType": "show_episode",
          "teaserGenre": "Kinder",
          "cluster": [
            "KIDS 6 bis 10 Jahre",
            "KIDS Jungs",
            "KIDS Mädchen",
            "Kids"
          ],
          "classification": [],
          "teaserSeason": "Staffel 2",
          "teaserEpisodeNumber": "Folge 25",
          "teaserEpisodeAirtime": "So. 04.10.2020, 08:00 Uhr",
          "teaserEpisodeName": "Folge 25"
        },
        "fsk": {
          "isVisible": false,
          "label": "ab 0",
          "minAge": 0
        },
        "headline": "Folge 25",
        "id": 3240553,
        "images": [
          {
            "dimension": "1x",
            "src": "https://ais-cf.tvnow.de/tvnow/movie/3240553/300x0/folge-25.jpg",
            "path": "https://ais-cf.tvnow.de/tvnow/movie/3240553/",
            "filename": "folge-25"
          },
          {
            "dimension": "2x",
            "src": "https://ais-cf.tvnow.de/tvnow/movie/3240553/600x0/folge-25.jpg",
            "path": "https://ais-cf.tvnow.de/tvnow/movie/3240553/",
            "filename": "folge-25"
          },
          {
            "dimension": "4x",
            "src": "https://ais-cf.tvnow.de/tvnow/movie/3240553/1200x0/folge-25.jpg",
            "path": "https://ais-cf.tvnow.de/tvnow/movie/3240553/",
            "filename": "folge-25"
          }
        ],
        "imagesHover": [
          {
            "dimension": "1x",
            "src": "https://ais-cf.tvnow.de/tvnow/movie/3240553/300x0/folge-25.jpg",
            "path": "https://ais-cf.tvnow.de/tvnow/movie/3240553/",
            "filename": "folge-25"
          },
          {
            "dimension": "2x",
            "src": "https://ais-cf.tvnow.de/tvnow/movie/3240553/600x0/folge-25.jpg",
            "path": "https://ais-cf.tvnow.de/tvnow/movie/3240553/",
            "filename": "folge-25"
          },
          {
            "dimension": "4x",
            "src": "https://ais-cf.tvnow.de/tvnow/movie/3240553/1200x0/folge-25.jpg",
            "path": "https://ais-cf.tvnow.de/tvnow/movie/3240553/",
            "filename": "folge-25"
          }
        ],
        "isPremium": true,
        "overlays": [
          "premium"
        ],
        "seoUrl": "super-toy-club",
        "subheadline": "Folge 25",
        "text": "Staffel 2, Folge 25 | So. 04.10.2020, 08:00 Uhr",
        "type": "show",
        "url": "/shows/super-toy-club-18042/staffel-2/episode-25-folge-25-3240553",
        "videoId": 3240553
      },
      {
        "buttons": [
          {
            "display": true,
            "formatId": 18042,
            "text": null,
            "type": "favorites"
          },
          {
            "display": true,
            "text": "Jetzt ansehen",
            "type": "play",
            "url": "/shows/super-toy-club-18042/staffel-2/episode-26-folge-26-3240542"
          }
        ],
        "ecommerce": {
          "teaserFormatName": "Super Toy Club",
          "teaserId": "show_episode_3240542",
          "teaserName": "Super Toy Club | Staffel 2 | Folge 26 | Folge 26",
          "teaserPayType": "paid",
          "teaserType": "show_episode",
          "teaserGenre": "Kinder",
          "cluster": [
            "KIDS 6 bis 10 Jahre",
            "KIDS Jungs",
            "KIDS Mädchen",
            "Kids"
          ],
          "classification": [],
          "teaserSeason": "Staffel 2",
          "teaserEpisodeNumber": "Folge 26",
          "teaserEpisodeAirtime": "Sa. 23.05.2020, 09:00 Uhr",
          "teaserEpisodeName": "Folge 26"
        },
        "fsk": {
          "isVisible": false,
          "label": "ab 0",
          "minAge": 0
        },
        "headline": "Folge 26",
        "id": 3240542,
        "images": [
          {
            "dimension": "1x",
            "src": "https://ais-cf.tvnow.de/tvnow/movie/3240542/300x0/folge-26.jpg",
            "path": "https://ais-cf.tvnow.de/tvnow/movie/3240542/",
            "filename": "folge-26"
          },
          {
            "dimension": "2x",
            "src": "https://ais-cf.tvnow.de/tvnow/movie/3240542/600x0/folge-26.jpg",
            "path": "https://ais-cf.tvnow.de/tvnow/movie/3240542/",
            "filename": "folge-26"
          },
          {
            "dimension": "4x",
            "src": "https://ais-cf.tvnow.de/tvnow/movie/3240542/1200x0/folge-26.jpg",
            "path": "https://ais-cf.tvnow.de/tvnow/movie/3240542/",
            "filename": "folge-26"
          }
        ],
        "imagesHover": [
          {
            "dimension": "1x",
            "src": "https://ais-cf.tvnow.de/tvnow/movie/3240542/300x0/folge-26.jpg",
            "path": "https://ais-cf.tvnow.de/tvnow/movie/3240542/",
            "filename": "folge-26"
          },
          {
            "dimension": "2x",
            "src": "https://ais-cf.tvnow.de/tvnow/movie/3240542/600x0/folge-26.jpg",
            "path": "https://ais-cf.tvnow.de/tvnow/movie/3240542/",
            "filename": "folge-26"
          },
          {
            "dimension": "4x",
            "src": "https://ais-cf.tvnow.de/tvnow/movie/3240542/1200x0/folge-26.jpg",
            "path": "https://ais-cf.tvnow.de/tvnow/movie/3240542/",
            "filename": "folge-26"
          }
        ],
        "isPremium": true,
        "overlays": [
          "premium"
        ],
        "seoUrl": "super-toy-club",
        "subheadline": "Folge 26",
        "text": "Staffel 2, Folge 26 | Sa. 23.05.2020, 09:00 Uhr",
        "type": "show",
        "url": "/shows/super-toy-club-18042/staffel-2/episode-26-folge-26-3240542",
        "videoId": 3240542
      },
      {
        "buttons": [
          {
            "display": true,
            "formatId": 18042,
            "text": null,
            "type": "favorites"
          },
          {
            "display": true,
            "text": "Jetzt ansehen",
            "type": "play",
            "url": "/shows/super-toy-club-18042/staffel-2/episode-27-folge-27-3240552"
          }
        ],
        "ecommerce": {
          "teaserFormatName": "Super Toy Club",
          "teaserId": "show_episode_3240552",
          "teaserName": "Super Toy Club | Staffel 2 | Folge 27 | Folge 27",
          "teaserPayType": "paid",
          "teaserType": "show_episode",
          "teaserGenre": "Kinder",
          "cluster": [
            "KIDS 6 bis 10 Jahre",
            "KIDS Jungs",
            "KIDS Mädchen",
            "Kids"
          ],
          "classification": [],
          "teaserSeason": "Staffel 2",
          "teaserEpisodeNumber": "Folge 27",
          "teaserEpisodeAirtime": "So. 24.05.2020, 09:00 Uhr",
          "teaserEpisodeName": "Folge 27"
        },
        "fsk": {
          "isVisible": false,
          "label": "ab 0",
          "minAge": 0
        },
        "headline": "Folge 27",
        "id": 3240552,
        "images": [
          {
            "dimension": "1x",
            "src": "https://ais-cf.tvnow.de/tvnow/movie/3240552/300x0/folge-27.jpg",
            "path": "https://ais-cf.tvnow.de/tvnow/movie/3240552/",
            "filename": "folge-27"
          },
          {
            "dimension": "2x",
            "src": "https://ais-cf.tvnow.de/tvnow/movie/3240552/600x0/folge-27.jpg",
            "path": "https://ais-cf.tvnow.de/tvnow/movie/3240552/",
            "filename": "folge-27"
          },
          {
            "dimension": "4x",
            "src": "https://ais-cf.tvnow.de/tvnow/movie/3240552/1200x0/folge-27.jpg",
            "path": "https://ais-cf.tvnow.de/tvnow/movie/3240552/",
            "filename": "folge-27"
          }
        ],
        "imagesHover": [
          {
            "dimension": "1x",
            "src": "https://ais-cf.tvnow.de/tvnow/movie/3240552/300x0/folge-27.jpg",
            "path": "https://ais-cf.tvnow.de/tvnow/movie/3240552/",
            "filename": "folge-27"
          },
          {
            "dimension": "2x",
            "src": "https://ais-cf.tvnow.de/tvnow/movie/3240552/600x0/folge-27.jpg",
            "path": "https://ais-cf.tvnow.de/tvnow/movie/3240552/",
            "filename": "folge-27"
          },
          {
            "dimension": "4x",
            "src": "https://ais-cf.tvnow.de/tvnow/movie/3240552/1200x0/folge-27.jpg",
            "path": "https://ais-cf.tvnow.de/tvnow/movie/3240552/",
            "filename": "folge-27"
          }
        ],
        "isPremium": true,
        "overlays": [
          "premium"
        ],
        "seoUrl": "super-toy-club",
        "subheadline": "Folge 27",
        "text": "Staffel 2, Folge 27 | So. 24.05.2020, 09:00 Uhr",
        "type": "show",
        "url": "/shows/super-toy-club-18042/staffel-2/episode-27-folge-27-3240552",
        "videoId": 3240552
      },
      {
        "buttons": [
          {
            "display": true,
            "formatId": 18042,
            "text": null,
            "type": "favorites"
          },
          {
            "display": true,
            "text": "Jetzt ansehen",
            "type": "play",
            "url": "/shows/super-toy-club-18042/staffel-2/episode-28-folge-28-3240470"
          }
        ],
        "ecommerce": {
          "teaserFormatName": "Super Toy Club",
          "teaserId": "show_episode_3240470",
          "teaserName": "Super Toy Club | Staffel 2 | Folge 28 | Folge 28",
          "teaserPayType": "paid",
          "teaserType": "show_episode",
          "teaserGenre": "Kinder",
          "cluster": [
            "KIDS 6 bis 10 Jahre",
            "KIDS Jungs",
            "KIDS Mädchen",
            "Kids"
          ],
          "classification": [],
          "teaserSeason": "Staffel 2",
          "teaserEpisodeNumber": "Folge 28",
          "teaserEpisodeAirtime": "Sa. 30.05.2020, 09:00 Uhr",
          "teaserEpisodeName": "Folge 28"
        },
        "fsk": {
          "isVisible": false,
          "label": "ab 0",
          "minAge": 0
        },
        "headline": "Folge 28",
        "id": 3240470,
        "images": [
          {
            "dimension": "1x",
            "src": "https://ais-cf.tvnow.de/tvnow/movie/3240470/300x0/folge-28.jpg",
            "path": "https://ais-cf.tvnow.de/tvnow/movie/3240470/",
            "filename": "folge-28"
          },
          {
            "dimension": "2x",
            "src": "https://ais-cf.tvnow.de/tvnow/movie/3240470/600x0/folge-28.jpg",
            "path": "https://ais-cf.tvnow.de/tvnow/movie/3240470/",
            "filename": "folge-28"
          },
          {
            "dimension": "4x",
            "src": "https://ais-cf.tvnow.de/tvnow/movie/3240470/1200x0/folge-28.jpg",
            "path": "https://ais-cf.tvnow.de/tvnow/movie/3240470/",
            "filename": "folge-28"
          }
        ],
        "imagesHover": [
          {
            "dimension": "1x",
            "src": "https://ais-cf.tvnow.de/tvnow/movie/3240470/300x0/folge-28.jpg",
            "path": "https://ais-cf.tvnow.de/tvnow/movie/3240470/",
            "filename": "folge-28"
          },
          {
            "dimension": "2x",
            "src": "https://ais-cf.tvnow.de/tvnow/movie/3240470/600x0/folge-28.jpg",
            "path": "https://ais-cf.tvnow.de/tvnow/movie/3240470/",
            "filename": "folge-28"
          },
          {
            "dimension": "4x",
            "src": "https://ais-cf.tvnow.de/tvnow/movie/3240470/1200x0/folge-28.jpg",
            "path": "https://ais-cf.tvnow.de/tvnow/movie/3240470/",
            "filename": "folge-28"
          }
        ],
        "isPremium": true,
        "overlays": [
          "premium"
        ],
        "seoUrl": "super-toy-club",
        "subheadline": "Folge 28",
        "text": "Staffel 2, Folge 28 | Sa. 30.05.2020, 09:00 Uhr",
        "type": "show",
        "url": "/shows/super-toy-club-18042/staffel-2/episode-28-folge-28-3240470",
        "videoId": 3240470
      },
      {
        "buttons": [
          {
            "display": true,
            "formatId": 18042,
            "text": null,
            "type": "favorites"
          },
          {
            "display": true,
            "text": "Jetzt ansehen",
            "type": "play",
            "url": "/shows/super-toy-club-18042/staffel-2/episode-29-die-fanta-hoerner-vs-suchsdorfer-boys-3240469"
          }
        ],
        "ecommerce": {
          "teaserFormatName": "Super Toy Club",
          "teaserId": "show_episode_3240469",
          "teaserName": "Super Toy Club | Staffel 2 | Folge 29 | \"Die Fanta-Hörner\" vs. \"Suchsdorfer Boys\" ",
          "teaserPayType": "paid",
          "teaserType": "show_episode",
          "teaserGenre": "Kinder",
          "cluster": [
            "KIDS 6 bis 10 Jahre",
            "KIDS Jungs",
            "KIDS Mädchen",
            "Kids"
          ],
          "classification": [],
          "teaserSeason": "Staffel 2",
          "teaserEpisodeNumber": "Folge 29",
          "teaserEpisodeAirtime": "Sa. 06.06.2020, 09:00 Uhr",
          "teaserEpisodeName": "\"Die Fanta-Hörner\" vs. \"Suchsdorfer Boys\" "
        },
        "fsk": {
          "isVisible": false,
          "label": "ab 0",
          "minAge": 0
        },
        "headline": "\"Die Fanta-Hörner\" vs. \"Suchsdorfer Boys\" ",
        "id": 3240469,
        "images": [
          {
            "dimension": "1x",
            "src": "https://ais-cf.tvnow.de/tvnow/movie/3240469/300x0/die-fanta-hoerner-vs-suchsdorfer-boys.jpg",
            "path": "https://ais-cf.tvnow.de/tvnow/movie/3240469/",
            "filename": "die-fanta-hoerner-vs-suchsdorfer-boys"
          },
          {
            "dimension": "2x",
            "src": "https://ais-cf.tvnow.de/tvnow/movie/3240469/600x0/die-fanta-hoerner-vs-suchsdorfer-boys.jpg",
            "path": "https://ais-cf.tvnow.de/tvnow/movie/3240469/",
            "filename": "die-fanta-hoerner-vs-suchsdorfer-boys"
          },
          {
            "dimension": "4x",
            "src": "https://ais-cf.tvnow.de/tvnow/movie/3240469/1200x0/die-fanta-hoerner-vs-suchsdorfer-boys.jpg",
            "path": "https://ais-cf.tvnow.de/tvnow/movie/3240469/",
            "filename": "die-fanta-hoerner-vs-suchsdorfer-boys"
          }
        ],
        "imagesHover": [
          {
            "dimension": "1x",
            "src": "https://ais-cf.tvnow.de/tvnow/movie/3240469/300x0/die-fanta-hoerner-vs-suchsdorfer-boys.jpg",
            "path": "https://ais-cf.tvnow.de/tvnow/movie/3240469/",
            "filename": "die-fanta-hoerner-vs-suchsdorfer-boys"
          },
          {
            "dimension": "2x",
            "src": "https://ais-cf.tvnow.de/tvnow/movie/3240469/600x0/die-fanta-hoerner-vs-suchsdorfer-boys.jpg",
            "path": "https://ais-cf.tvnow.de/tvnow/movie/3240469/",
            "filename": "die-fanta-hoerner-vs-suchsdorfer-boys"
          },
          {
            "dimension": "4x",
            "src": "https://ais-cf.tvnow.de/tvnow/movie/3240469/1200x0/die-fanta-hoerner-vs-suchsdorfer-boys.jpg",
            "path": "https://ais-cf.tvnow.de/tvnow/movie/3240469/",
            "filename": "die-fanta-hoerner-vs-suchsdorfer-boys"
          }
        ],
        "isPremium": true,
        "overlays": [
          "premium"
        ],
        "seoUrl": "super-toy-club",
        "subheadline": "\"Die Fanta-Hörner\" vs. \"Suchsdorfer Boys\" ",
        "text": "Staffel 2, Folge 29 | Sa. 06.06.2020, 09:00 Uhr",
        "type": "show",
        "url": "/shows/super-toy-club-18042/staffel-2/episode-29-die-fanta-hoerner-vs-suchsdorfer-boys-3240469",
        "videoId": 3240469
      },
      {
        "buttons": [
          {
            "display": true,
            "formatId": 18042,
            "text": null,
            "type": "favorites"
          },
          {
            "display": true,
            "text": "Jetzt ansehen",
            "type": "play",
            "url": "/shows/super-toy-club-18042/staffel-2/episode-30-die-tierlieben-vs-die-kraehen-3240475"
          }
        ],
        "ecommerce": {
          "teaserFormatName": "Super Toy Club",
          "teaserId": "show_episode_3240475",
          "teaserName": "Super Toy Club | Staffel 2 | Folge 30 | \"Die Tierlieben\" vs. \"Die Krähen\"",
          "teaserPayType": "paid",
          "teaserType": "show_episode",
          "teaserGenre": "Kinder",
          "cluster": [
            "KIDS 6 bis 10 Jahre",
            "KIDS Jungs",
            "KIDS Mädchen",
            "Kids"
          ],
          "classification": [],
          "teaserSeason": "Staffel 2",
          "teaserEpisodeNumber": "Folge 30",
          "teaserEpisodeAirtime": "So. 07.06.2020, 09:00 Uhr",
          "teaserEpisodeName": "\"Die Tierlieben\" vs. \"Die Krähen\""
        },
        "fsk": {
          "isVisible": false,
          "label": "ab 0",
          "minAge": 0
        },
        "headline": "\"Die Tierlieben\" vs. \"Die Krähen\"",
        "id": 3240475,
        "images": [
          {
            "dimension": "1x",
            "src": "https://ais-cf.tvnow.de/tvnow/movie/3240475/300x0/die-tierlieben-vs-die-kraehen.jpg",
            "path": "https://ais-cf.tvnow.de/tvnow/movie/3240475/",
            "filename": "die-tierlieben-vs-die-kraehen"
          },
          {
            "dimension": "2x",
            "src": "https://ais-cf.tvnow.de/tvnow/movie/3240475/600x0/die-tierlieben-vs-die-kraehen.jpg",
            "path": "https://ais-cf.tvnow.de/tvnow/movie/3240475/",
            "filename": "die-tierlieben-vs-die-kraehen"
          },
          {
            "dimension": "4x",
            "src": "https://ais-cf.tvnow.de/tvnow/movie/3240475/1200x0/die-tierlieben-vs-die-kraehen.jpg",
            "path": "https://ais-cf.tvnow.de/tvnow/movie/3240475/",
            "filename": "die-tierlieben-vs-die-kraehen"
          }
        ],
        "imagesHover": [
          {
            "dimension": "1x",
            "src": "https://ais-cf.tvnow.de/tvnow/movie/3240475/300x0/die-tierlieben-vs-die-kraehen.jpg",
            "path": "https://ais-cf.tvnow.de/tvnow/movie/3240475/",
            "filename": "die-tierlieben-vs-die-kraehen"
          },
          {
            "dimension": "2x",
            "src": "https://ais-cf.tvnow.de/tvnow/movie/3240475/600x0/die-tierlieben-vs-die-kraehen.jpg",
            "path": "https://ais-cf.tvnow.de/tvnow/movie/3240475/",
            "filename": "die-tierlieben-vs-die-kraehen"
          },
          {
            "dimension": "4x",
            "src": "https://ais-cf.tvnow.de/tvnow/movie/3240475/1200x0/die-tierlieben-vs-die-kraehen.jpg",
            "path": "https://ais-cf.tvnow.de/tvnow/movie/3240475/",
            "filename": "die-tierlieben-vs-die-kraehen"
          }
        ],
        "isPremium": true,
        "overlays": [
          "premium"
        ],
        "seoUrl": "super-toy-club",
        "subheadline": "\"Die Tierlieben\" vs. \"Die Krähen\"",
        "text": "Staffel 2, Folge 30 | So. 07.06.2020, 09:00 Uhr",
        "type": "show",
        "url": "/shows/super-toy-club-18042/staffel-2/episode-30-die-tierlieben-vs-die-kraehen-3240475",
        "videoId": 3240475
      },
      {
        "buttons": [
          {
            "display": true,
            "formatId": 18042,
            "text": null,
            "type": "favorites"
          },
          {
            "display": true,
            "text": "Jetzt ansehen",
            "type": "play",
            "url": "/shows/super-toy-club-18042/staffel-2/episode-31-folge-31-3240472"
          }
        ],
        "ecommerce": {
          "teaserFormatName": "Super Toy Club",
          "teaserId": "show_episode_3240472",
          "teaserName": "Super Toy Club | Staffel 2 | Folge 31 | Folge 31",
          "teaserPayType": "paid",
          "teaserType": "show_episode",
          "teaserGenre": "Kinder",
          "cluster": [
            "KIDS 6 bis 10 Jahre",
            "KIDS Jungs",
            "KIDS Mädchen",
            "Kids"
          ],
          "classification": [],
          "teaserSeason": "Staffel 2",
          "teaserEpisodeNumber": "Folge 31",
          "teaserEpisodeAirtime": "Sa. 13.06.2020, 09:00 Uhr",
          "teaserEpisodeName": "Folge 31"
        },
        "fsk": {
          "isVisible": false,
          "label": "ab 0",
          "minAge": 0
        },
        "headline": "Folge 31",
        "id": 3240472,
        "images": [
          {
            "dimension": "1x",
            "src": "https://ais-cf.tvnow.de/tvnow/movie/3240472/300x0/folge-31.jpg",
            "path": "https://ais-cf.tvnow.de/tvnow/movie/3240472/",
            "filename": "folge-31"
          },
          {
            "dimension": "2x",
            "src": "https://ais-cf.tvnow.de/tvnow/movie/3240472/600x0/folge-31.jpg",
            "path": "https://ais-cf.tvnow.de/tvnow/movie/3240472/",
            "filename": "folge-31"
          },
          {
            "dimension": "4x",
            "src": "https://ais-cf.tvnow.de/tvnow/movie/3240472/1200x0/folge-31.jpg",
            "path": "https://ais-cf.tvnow.de/tvnow/movie/3240472/",
            "filename": "folge-31"
          }
        ],
        "imagesHover": [
          {
            "dimension": "1x",
            "src": "https://ais-cf.tvnow.de/tvnow/movie/3240472/300x0/folge-31.jpg",
            "path": "https://ais-cf.tvnow.de/tvnow/movie/3240472/",
            "filename": "folge-31"
          },
          {
            "dimension": "2x",
            "src": "https://ais-cf.tvnow.de/tvnow/movie/3240472/600x0/folge-31.jpg",
            "path": "https://ais-cf.tvnow.de/tvnow/movie/3240472/",
            "filename": "folge-31"
          },
          {
            "dimension": "4x",
            "src": "https://ais-cf.tvnow.de/tvnow/movie/3240472/1200x0/folge-31.jpg",
            "path": "https://ais-cf.tvnow.de/tvnow/movie/3240472/",
            "filename": "folge-31"
          }
        ],
        "isPremium": true,
        "overlays": [
          "premium"
        ],
        "seoUrl": "super-toy-club",
        "subheadline": "Folge 31",
        "text": "Staffel 2, Folge 31 | Sa. 13.06.2020, 09:00 Uhr",
        "type": "show",
        "url": "/shows/super-toy-club-18042/staffel-2/episode-31-folge-31-3240472",
        "videoId": 3240472
      },
      {
        "buttons": [
          {
            "display": true,
            "formatId": 18042,
            "text": null,
            "type": "favorites"
          },
          {
            "display": true,
            "text": "Jetzt ansehen",
            "type": "play",
            "url": "/shows/super-toy-club-18042/staffel-2/episode-32-folge-32-3240473"
          }
        ],
        "ecommerce": {
          "teaserFormatName": "Super Toy Club",
          "teaserId": "show_episode_3240473",
          "teaserName": "Super Toy Club | Staffel 2 | Folge 32 | Folge 32",
          "teaserPayType": "paid",
          "teaserType": "show_episode",
          "teaserGenre": "Kinder",
          "cluster": [
            "KIDS 6 bis 10 Jahre",
            "KIDS Jungs",
            "KIDS Mädchen",
            "Kids"
          ],
          "classification": [],
          "teaserSeason": "Staffel 2",
          "teaserEpisodeNumber": "Folge 32",
          "teaserEpisodeAirtime": "So. 14.06.2020, 09:00 Uhr",
          "teaserEpisodeName": "Folge 32"
        },
        "fsk": {
          "isVisible": false,
          "label": "ab 0",
          "minAge": 0
        },
        "headline": "Folge 32",
        "id": 3240473,
        "images": [
          {
            "dimension": "1x",
            "src": "https://ais-cf.tvnow.de/tvnow/movie/3240473/300x0/folge-32.jpg",
            "path": "https://ais-cf.tvnow.de/tvnow/movie/3240473/",
            "filename": "folge-32"
          },
          {
            "dimension": "2x",
            "src": "https://ais-cf.tvnow.de/tvnow/movie/3240473/600x0/folge-32.jpg",
            "path": "https://ais-cf.tvnow.de/tvnow/movie/3240473/",
            "filename": "folge-32"
          },
          {
            "dimension": "4x",
            "src": "https://ais-cf.tvnow.de/tvnow/movie/3240473/1200x0/folge-32.jpg",
            "path": "https://ais-cf.tvnow.de/tvnow/movie/3240473/",
            "filename": "folge-32"
          }
        ],
        "imagesHover": [
          {
            "dimension": "1x",
            "src": "https://ais-cf.tvnow.de/tvnow/movie/3240473/300x0/folge-32.jpg",
            "path": "https://ais-cf.tvnow.de/tvnow/movie/3240473/",
            "filename": "folge-32"
          },
          {
            "dimension": "2x",
            "src": "https://ais-cf.tvnow.de/tvnow/movie/3240473/600x0/folge-32.jpg",
            "path": "https://ais-cf.tvnow.de/tvnow/movie/3240473/",
            "filename": "folge-32"
          },
          {
            "dimension": "4x",
            "src": "https://ais-cf.tvnow.de/tvnow/movie/3240473/1200x0/folge-32.jpg",
            "path": "https://ais-cf.tvnow.de/tvnow/movie/3240473/",
            "filename": "folge-32"
          }
        ],
        "isPremium": true,
        "overlays": [
          "premium"
        ],
        "seoUrl": "super-toy-club",
        "subheadline": "Folge 32",
        "text": "Staffel 2, Folge 32 | So. 14.06.2020, 09:00 Uhr",
        "type": "show",
        "url": "/shows/super-toy-club-18042/staffel-2/episode-32-folge-32-3240473",
        "videoId": 3240473
      },
      {
        "buttons": [
          {
            "display": true,
            "formatId": 18042,
            "text": null,
            "type": "favorites"
          },
          {
            "display": true,
            "text": "Jetzt ansehen",
            "type": "play",
            "url": "/shows/super-toy-club-18042/staffel-2/episode-33-folge-33-3217087"
          }
        ],
        "ecommerce": {
          "teaserFormatName": "Super Toy Club",
          "teaserId": "show_episode_3217087",
          "teaserName": "Super Toy Club | Staffel 2 | Folge 33 | Folge 33",
          "teaserPayType": "paid",
          "teaserType": "show_episode",
          "teaserGenre": "Kinder",
          "cluster": [
            "KIDS 6 bis 10 Jahre",
            "KIDS Jungs",
            "KIDS Mädchen",
            "Kids"
          ],
          "classification": [],
          "teaserSeason": "Staffel 2",
          "teaserEpisodeNumber": "Folge 33",
          "teaserEpisodeAirtime": "Sa. 20.06.2020, 09:00 Uhr",
          "teaserEpisodeName": "Folge 33"
        },
        "fsk": {
          "isVisible": false,
          "label": "ab 0",
          "minAge": 0
        },
        "headline": "Folge 33",
        "id": 3217087,
        "images": [
          {
            "dimension": "1x",
            "src": "https://ais-cf.tvnow.de/tvnow/movie/3217087/300x0/folge-33.jpg",
            "path": "https://ais-cf.tvnow.de/tvnow/movie/3217087/",
            "filename": "folge-33"
          },
          {
            "dimension": "2x",
            "src": "https://ais-cf.tvnow.de/tvnow/movie/3217087/600x0/folge-33.jpg",
            "path": "https://ais-cf.tvnow.de/tvnow/movie/3217087/",
            "filename": "folge-33"
          },
          {
            "dimension": "4x",
            "src": "https://ais-cf.tvnow.de/tvnow/movie/3217087/1200x0/folge-33.jpg",
            "path": "https://ais-cf.tvnow.de/tvnow/movie/3217087/",
            "filename": "folge-33"
          }
        ],
        "imagesHover": [
          {
            "dimension": "1x",
            "src": "https://ais-cf.tvnow.de/tvnow/movie/3217087/300x0/folge-33.jpg",
            "path": "https://ais-cf.tvnow.de/tvnow/movie/3217087/",
            "filename": "folge-33"
          },
          {
            "dimension": "2x",
            "src": "https://ais-cf.tvnow.de/tvnow/movie/3217087/600x0/folge-33.jpg",
            "path": "https://ais-cf.tvnow.de/tvnow/movie/3217087/",
            "filename": "folge-33"
          },
          {
            "dimension": "4x",
            "src": "https://ais-cf.tvnow.de/tvnow/movie/3217087/1200x0/folge-33.jpg",
            "path": "https://ais-cf.tvnow.de/tvnow/movie/3217087/",
            "filename": "folge-33"
          }
        ],
        "isPremium": true,
        "overlays": [
          "premium"
        ],
        "seoUrl": "super-toy-club",
        "subheadline": "Folge 33",
        "text": "Staffel 2, Folge 33 | Sa. 20.06.2020, 09:00 Uhr",
        "type": "show",
        "url": "/shows/super-toy-club-18042/staffel-2/episode-33-folge-33-3217087",
        "videoId": 3217087
      },
      {
        "buttons": [
          {
            "display": true,
            "formatId": 18042,
            "text": null,
            "type": "favorites"
          },
          {
            "display": true,
            "text": "Jetzt ansehen",
            "type": "play",
            "url": "/shows/super-toy-club-18042/staffel-2/episode-34-folge-34-3214872"
          }
        ],
        "ecommerce": {
          "teaserFormatName": "Super Toy Club",
          "teaserId": "show_episode_3214872",
          "teaserName": "Super Toy Club | Staffel 2 | Folge 34 | Folge 34",
          "teaserPayType": "paid",
          "teaserType": "show_episode",
          "teaserGenre": "Kinder",
          "cluster": [
            "KIDS 6 bis 10 Jahre",
            "KIDS Jungs",
            "KIDS Mädchen",
            "Kids"
          ],
          "classification": [],
          "teaserSeason": "Staffel 2",
          "teaserEpisodeNumber": "Folge 34",
          "teaserEpisodeAirtime": "So. 21.06.2020, 09:00 Uhr",
          "teaserEpisodeName": "Folge 34"
        },
        "fsk": {
          "isVisible": false,
          "label": "ab 0",
          "minAge": 0
        },
        "headline": "Folge 34",
        "id": 3214872,
        "images": [
          {
            "dimension": "1x",
            "src": "https://ais-cf.tvnow.de/tvnow/movie/3214872/300x0/folge-34.jpg",
            "path": "https://ais-cf.tvnow.de/tvnow/movie/3214872/",
            "filename": "folge-34"
          },
          {
            "dimension": "2x",
            "src": "https://ais-cf.tvnow.de/tvnow/movie/3214872/600x0/folge-34.jpg",
            "path": "https://ais-cf.tvnow.de/tvnow/movie/3214872/",
            "filename": "folge-34"
          },
          {
            "dimension": "4x",
            "src": "https://ais-cf.tvnow.de/tvnow/movie/3214872/1200x0/folge-34.jpg",
            "path": "https://ais-cf.tvnow.de/tvnow/movie/3214872/",
            "filename": "folge-34"
          }
        ],
        "imagesHover": [
          {
            "dimension": "1x",
            "src": "https://ais-cf.tvnow.de/tvnow/movie/3214872/300x0/folge-34.jpg",
            "path": "https://ais-cf.tvnow.de/tvnow/movie/3214872/",
            "filename": "folge-34"
          },
          {
            "dimension": "2x",
            "src": "https://ais-cf.tvnow.de/tvnow/movie/3214872/600x0/folge-34.jpg",
            "path": "https://ais-cf.tvnow.de/tvnow/movie/3214872/",
            "filename": "folge-34"
          },
          {
            "dimension": "4x",
            "src": "https://ais-cf.tvnow.de/tvnow/movie/3214872/1200x0/folge-34.jpg",
            "path": "https://ais-cf.tvnow.de/tvnow/movie/3214872/",
            "filename": "folge-34"
          }
        ],
        "isPremium": true,
        "overlays": [
          "premium"
        ],
        "seoUrl": "super-toy-club",
        "subheadline": "Folge 34",
        "text": "Staffel 2, Folge 34 | So. 21.06.2020, 09:00 Uhr",
        "type": "show",
        "url": "/shows/super-toy-club-18042/staffel-2/episode-34-folge-34-3214872",
        "videoId": 3214872
      },
      {
        "buttons": [
          {
            "display": true,
            "formatId": 18042,
            "text": null,
            "type": "favorites"
          },
          {
            "display": true,
            "text": "Jetzt ansehen",
            "type": "play",
            "url": "/shows/super-toy-club-18042/staffel-2/episode-35-folge-35-3239107"
          }
        ],
        "ecommerce": {
          "teaserFormatName": "Super Toy Club",
          "teaserId": "show_episode_3239107",
          "teaserName": "Super Toy Club | Staffel 2 | Folge 35 | Folge 35",
          "teaserPayType": "paid",
          "teaserType": "show_episode",
          "teaserGenre": "Kinder",
          "cluster": [
            "KIDS 6 bis 10 Jahre",
            "KIDS Jungs",
            "KIDS Mädchen",
            "Kids"
          ],
          "classification": [],
          "teaserSeason": "Staffel 2",
          "teaserEpisodeNumber": "Folge 35",
          "teaserEpisodeAirtime": "Sa. 27.06.2020, 09:00 Uhr",
          "teaserEpisodeName": "Folge 35"
        },
        "fsk": {
          "isVisible": false,
          "label": "ab 0",
          "minAge": 0
        },
        "headline": "Folge 35",
        "id": 3239107,
        "images": [
          {
            "dimension": "1x",
            "src": "https://ais-cf.tvnow.de/tvnow/movie/3239107/300x0/folge-35.jpg",
            "path": "https://ais-cf.tvnow.de/tvnow/movie/3239107/",
            "filename": "folge-35"
          },
          {
            "dimension": "2x",
            "src": "https://ais-cf.tvnow.de/tvnow/movie/3239107/600x0/folge-35.jpg",
            "path": "https://ais-cf.tvnow.de/tvnow/movie/3239107/",
            "filename": "folge-35"
          },
          {
            "dimension": "4x",
            "src": "https://ais-cf.tvnow.de/tvnow/movie/3239107/1200x0/folge-35.jpg",
            "path": "https://ais-cf.tvnow.de/tvnow/movie/3239107/",
            "filename": "folge-35"
          }
        ],
        "imagesHover": [
          {
            "dimension": "1x",
            "src": "https://ais-cf.tvnow.de/tvnow/movie/3239107/300x0/folge-35.jpg",
            "path": "https://ais-cf.tvnow.de/tvnow/movie/3239107/",
            "filename": "folge-35"
          },
          {
            "dimension": "2x",
            "src": "https://ais-cf.tvnow.de/tvnow/movie/3239107/600x0/folge-35.jpg",
            "path": "https://ais-cf.tvnow.de/tvnow/movie/3239107/",
            "filename": "folge-35"
          },
          {
            "dimension": "4x",
            "src": "https://ais-cf.tvnow.de/tvnow/movie/3239107/1200x0/folge-35.jpg",
            "path": "https://ais-cf.tvnow.de/tvnow/movie/3239107/",
            "filename": "folge-35"
          }
        ],
        "isPremium": true,
        "overlays": [
          "premium"
        ],
        "seoUrl": "super-toy-club",
        "subheadline": "Folge 35",
        "text": "Staffel 2, Folge 35 | Sa. 27.06.2020, 09:00 Uhr",
        "type": "show",
        "url": "/shows/super-toy-club-18042/staffel-2/episode-35-folge-35-3239107",
        "videoId": 3239107
      },
      {
        "buttons": [
          {
            "display": true,
            "formatId": 18042,
            "text": null,
            "type": "favorites"
          },
          {
            "display": true,
            "text": "Jetzt ansehen",
            "type": "play",
            "url": "/shows/super-toy-club-18042/staffel-2/episode-36-folge-36-3228673"
          }
        ],
        "ecommerce": {
          "teaserFormatName": "Super Toy Club",
          "teaserId": "show_episode_3228673",
          "teaserName": "Super Toy Club | Staffel 2 | Folge 36 | Folge 36",
          "teaserPayType": "paid",
          "teaserType": "show_episode",
          "teaserGenre": "Kinder",
          "cluster": [
            "KIDS 6 bis 10 Jahre",
            "KIDS Jungs",
            "KIDS Mädchen",
            "Kids"
          ],
          "classification": [],
          "teaserSeason": "Staffel 2",
          "teaserEpisodeNumber": "Folge 36",
          "teaserEpisodeAirtime": "So. 28.06.2020, 09:00 Uhr",
          "teaserEpisodeName": "Folge 36"
        },
        "fsk": {
          "isVisible": false,
          "label": "ab 0",
          "minAge": 0
        },
        "headline": "Folge 36",
        "id": 3228673,
        "images": [
          {
            "dimension": "1x",
            "src": "https://ais-cf.tvnow.de/tvnow/movie/3228673/300x0/folge-36.jpg",
            "path": "https://ais-cf.tvnow.de/tvnow/movie/3228673/",
            "filename": "folge-36"
          },
          {
            "dimension": "2x",
            "src": "https://ais-cf.tvnow.de/tvnow/movie/3228673/600x0/folge-36.jpg",
            "path": "https://ais-cf.tvnow.de/tvnow/movie/3228673/",
            "filename": "folge-36"
          },
          {
            "dimension": "4x",
            "src": "https://ais-cf.tvnow.de/tvnow/movie/3228673/1200x0/folge-36.jpg",
            "path": "https://ais-cf.tvnow.de/tvnow/movie/3228673/",
            "filename": "folge-36"
          }
        ],
        "imagesHover": [
          {
            "dimension": "1x",
            "src": "https://ais-cf.tvnow.de/tvnow/movie/3228673/300x0/folge-36.jpg",
            "path": "https://ais-cf.tvnow.de/tvnow/movie/3228673/",
            "filename": "folge-36"
          },
          {
            "dimension": "2x",
            "src": "https://ais-cf.tvnow.de/tvnow/movie/3228673/600x0/folge-36.jpg",
            "path": "https://ais-cf.tvnow.de/tvnow/movie/3228673/",
            "filename": "folge-36"
          },
          {
            "dimension": "4x",
            "src": "https://ais-cf.tvnow.de/tvnow/movie/3228673/1200x0/folge-36.jpg",
            "path": "https://ais-cf.tvnow.de/tvnow/movie/3228673/",
            "filename": "folge-36"
          }
        ],
        "isPremium": true,
        "overlays": [
          "premium"
        ],
        "seoUrl": "super-toy-club",
        "subheadline": "Folge 36",
        "text": "Staffel 2, Folge 36 | So. 28.06.2020, 09:00 Uhr",
        "type": "show",
        "url": "/shows/super-toy-club-18042/staffel-2/episode-36-folge-36-3228673",
        "videoId": 3228673
      },
      {
        "buttons": [
          {
            "display": true,
            "formatId": 18042,
            "text": null,
            "type": "favorites"
          },
          {
            "display": true,
            "text": "Jetzt ansehen",
            "type": "play",
            "url": "/shows/super-toy-club-18042/staffel-2/episode-37-folge-37-3243665"
          }
        ],
        "ecommerce": {
          "teaserFormatName": "Super Toy Club",
          "teaserId": "show_episode_3243665",
          "teaserName": "Super Toy Club | Staffel 2 | Folge 37 | Folge 37",
          "teaserPayType": "paid",
          "teaserType": "show_episode",
          "teaserGenre": "Kinder",
          "cluster": [
            "KIDS 6 bis 10 Jahre",
            "KIDS Jungs",
            "KIDS Mädchen",
            "Kids"
          ],
          "classification": [],
          "teaserSeason": "Staffel 2",
          "teaserEpisodeNumber": "Folge 37",
          "teaserEpisodeAirtime": "Sa. 04.07.2020, 09:00 Uhr",
          "teaserEpisodeName": "Folge 37"
        },
        "fsk": {
          "isVisible": false,
          "label": "ab 0",
          "minAge": 0
        },
        "headline": "Folge 37",
        "id": 3243665,
        "images": [
          {
            "dimension": "1x",
            "src": "https://ais-cf.tvnow.de/tvnow/movie/3243665/300x0/folge-37.jpg",
            "path": "https://ais-cf.tvnow.de/tvnow/movie/3243665/",
            "filename": "folge-37"
          },
          {
            "dimension": "2x",
            "src": "https://ais-cf.tvnow.de/tvnow/movie/3243665/600x0/folge-37.jpg",
            "path": "https://ais-cf.tvnow.de/tvnow/movie/3243665/",
            "filename": "folge-37"
          },
          {
            "dimension": "4x",
            "src": "https://ais-cf.tvnow.de/tvnow/movie/3243665/1200x0/folge-37.jpg",
            "path": "https://ais-cf.tvnow.de/tvnow/movie/3243665/",
            "filename": "folge-37"
          }
        ],
        "imagesHover": [
          {
            "dimension": "1x",
            "src": "https://ais-cf.tvnow.de/tvnow/movie/3243665/300x0/folge-37.jpg",
            "path": "https://ais-cf.tvnow.de/tvnow/movie/3243665/",
            "filename": "folge-37"
          },
          {
            "dimension": "2x",
            "src": "https://ais-cf.tvnow.de/tvnow/movie/3243665/600x0/folge-37.jpg",
            "path": "https://ais-cf.tvnow.de/tvnow/movie/3243665/",
            "filename": "folge-37"
          },
          {
            "dimension": "4x",
            "src": "https://ais-cf.tvnow.de/tvnow/movie/3243665/1200x0/folge-37.jpg",
            "path": "https://ais-cf.tvnow.de/tvnow/movie/3243665/",
            "filename": "folge-37"
          }
        ],
        "isPremium": true,
        "overlays": [
          "premium"
        ],
        "seoUrl": "super-toy-club",
        "subheadline": "Folge 37",
        "text": "Staffel 2, Folge 37 | Sa. 04.07.2020, 09:00 Uhr",
        "type": "show",
        "url": "/shows/super-toy-club-18042/staffel-2/episode-37-folge-37-3243665",
        "videoId": 3243665
      },
      {
        "buttons": [
          {
            "display": true,
            "formatId": 18042,
            "text": null,
            "type": "favorites"
          },
          {
            "display": true,
            "text": "Jetzt ansehen",
            "type": "play",
            "url": "/shows/super-toy-club-18042/staffel-2/episode-38-folge-38-3259414"
          }
        ],
        "ecommerce": {
          "teaserFormatName": "Super Toy Club",
          "teaserId": "show_episode_3259414",
          "teaserName": "Super Toy Club | Staffel 2 | Folge 38 | Folge 38",
          "teaserPayType": "paid",
          "teaserType": "show_episode",
          "teaserGenre": "Kinder",
          "cluster": [
            "KIDS 6 bis 10 Jahre",
            "KIDS Jungs",
            "KIDS Mädchen",
            "Kids"
          ],
          "classification": [],
          "teaserSeason": "Staffel 2",
          "teaserEpisodeNumber": "Folge 38",
          "teaserEpisodeAirtime": "So. 05.07.2020, 09:00 Uhr",
          "teaserEpisodeName": "Folge 38"
        },
        "fsk": {
          "isVisible": false,
          "label": "ab 0",
          "minAge": 0
        },
        "headline": "Folge 38",
        "id": 3259414,
        "images": [
          {
            "dimension": "1x",
            "src": "https://ais-cf.tvnow.de/tvnow/movie/3259414/300x0/folge-38.jpg",
            "path": "https://ais-cf.tvnow.de/tvnow/movie/3259414/",
            "filename": "folge-38"
          },
          {
            "dimension": "2x",
            "src": "https://ais-cf.tvnow.de/tvnow/movie/3259414/600x0/folge-38.jpg",
            "path": "https://ais-cf.tvnow.de/tvnow/movie/3259414/",
            "filename": "folge-38"
          },
          {
            "dimension": "4x",
            "src": "https://ais-cf.tvnow.de/tvnow/movie/3259414/1200x0/folge-38.jpg",
            "path": "https://ais-cf.tvnow.de/tvnow/movie/3259414/",
            "filename": "folge-38"
          }
        ],
        "imagesHover": [
          {
            "dimension": "1x",
            "src": "https://ais-cf.tvnow.de/tvnow/movie/3259414/300x0/folge-38.jpg",
            "path": "https://ais-cf.tvnow.de/tvnow/movie/3259414/",
            "filename": "folge-38"
          },
          {
            "dimension": "2x",
            "src": "https://ais-cf.tvnow.de/tvnow/movie/3259414/600x0/folge-38.jpg",
            "path": "https://ais-cf.tvnow.de/tvnow/movie/3259414/",
            "filename": "folge-38"
          },
          {
            "dimension": "4x",
            "src": "https://ais-cf.tvnow.de/tvnow/movie/3259414/1200x0/folge-38.jpg",
            "path": "https://ais-cf.tvnow.de/tvnow/movie/3259414/",
            "filename": "folge-38"
          }
        ],
        "isPremium": true,
        "overlays": [
          "premium"
        ],
        "seoUrl": "super-toy-club",
        "subheadline": "Folge 38",
        "text": "Staffel 2, Folge 38 | So. 05.07.2020, 09:00 Uhr",
        "type": "show",
        "url": "/shows/super-toy-club-18042/staffel-2/episode-38-folge-38-3259414",
        "videoId": 3259414
      },
      {
        "buttons": [
          {
            "display": true,
            "formatId": 18042,
            "text": null,
            "type": "favorites"
          },
          {
            "display": true,
            "text": "Jetzt ansehen",
            "type": "play",
            "url": "/shows/super-toy-club-18042/staffel-2/episode-39-folge-39-3240571"
          }
        ],
        "ecommerce": {
          "teaserFormatName": "Super Toy Club",
          "teaserId": "show_episode_3240571",
          "teaserName": "Super Toy Club | Staffel 2 | Folge 39 | Folge 39",
          "teaserPayType": "paid",
          "teaserType": "show_episode",
          "teaserGenre": "Kinder",
          "cluster": [
            "KIDS 6 bis 10 Jahre",
            "KIDS Jungs",
            "KIDS Mädchen",
            "Kids"
          ],
          "classification": [],
          "teaserSeason": "Staffel 2",
          "teaserEpisodeNumber": "Folge 39",
          "teaserEpisodeAirtime": "Sa. 11.07.2020, 09:00 Uhr",
          "teaserEpisodeName": "Folge 39"
        },
        "fsk": {
          "isVisible": false,
          "label": "ab 0",
          "minAge": 0
        },
        "headline": "Folge 39",
        "id": 3240571,
        "images": [
          {
            "dimension": "1x",
            "src": "https://ais-cf.tvnow.de/tvnow/movie/3240571/300x0/folge-39.jpg",
            "path": "https://ais-cf.tvnow.de/tvnow/movie/3240571/",
            "filename": "folge-39"
          },
          {
            "dimension": "2x",
            "src": "https://ais-cf.tvnow.de/tvnow/movie/3240571/600x0/folge-39.jpg",
            "path": "https://ais-cf.tvnow.de/tvnow/movie/3240571/",
            "filename": "folge-39"
          },
          {
            "dimension": "4x",
            "src": "https://ais-cf.tvnow.de/tvnow/movie/3240571/1200x0/folge-39.jpg",
            "path": "https://ais-cf.tvnow.de/tvnow/movie/3240571/",
            "filename": "folge-39"
          }
        ],
        "imagesHover": [
          {
            "dimension": "1x",
            "src": "https://ais-cf.tvnow.de/tvnow/movie/3240571/300x0/folge-39.jpg",
            "path": "https://ais-cf.tvnow.de/tvnow/movie/3240571/",
            "filename": "folge-39"
          },
          {
            "dimension": "2x",
            "src": "https://ais-cf.tvnow.de/tvnow/movie/3240571/600x0/folge-39.jpg",
            "path": "https://ais-cf.tvnow.de/tvnow/movie/3240571/",
            "filename": "folge-39"
          },
          {
            "dimension": "4x",
            "src": "https://ais-cf.tvnow.de/tvnow/movie/3240571/1200x0/folge-39.jpg",
            "path": "https://ais-cf.tvnow.de/tvnow/movie/3240571/",
            "filename": "folge-39"
          }
        ],
        "isPremium": true,
        "overlays": [
          "premium"
        ],
        "seoUrl": "super-toy-club",
        "subheadline": "Folge 39",
        "text": "Staffel 2, Folge 39 | Sa. 11.07.2020, 09:00 Uhr",
        "type": "show",
        "url": "/shows/super-toy-club-18042/staffel-2/episode-39-folge-39-3240571",
        "videoId": 3240571
      }
    ],
    "format_navigation": {
      "season": 2
    },
    "navigationType": "season"
  },
  {
    "ecommerce": {
      "rowCategory": "small_teaser",
      "rowId": "na",
      "rowName": "Staffel 3"
    },
    "id": null,
    "label": null,
    "moduleLayout": "format_episode",
    "moduleUrl": "/module/teaserrow/format/episode/18042",
    "type": "teaserrow",
    "items": [
      {
        "buttons": [
          {
            "display": true,
            "formatId": 18042,
            "text": null,
            "type": "favorites"
          },
          {
            "display": true,
            "text": "Jetzt ansehen",
            "type": "play",
            "url": "/shows/super-toy-club-18042/staffel-3/episode-56-folge-56-3437557"
          }
        ],
        "ecommerce": {
          "teaserFormatName": "Super Toy Club",
          "teaserId": "show_episode_3437557",
          "teaserName": "Super Toy Club | Staffel 3 | Folge 56 | Folge 56",
          "teaserPayType": "free",
          "teaserType": "show_episode",
          "teaserGenre": "Kinder",
          "cluster": [
            "KIDS 6 bis 10 Jahre",
            "KIDS Jungs",
            "KIDS Mädchen",
            "Kids"
          ],
          "classification": [],
          "teaserSeason": "Staffel 3",
          "teaserEpisodeNumber": "Folge 56",
          "teaserEpisodeAirtime": "Sa. 10.10.2020, 08:00 Uhr",
          "teaserEpisodeName": "Folge 56"
        },
        "fsk": {
          "isVisible": false,
          "label": "ab 0",
          "minAge": 0
        },
        "headline": "Folge 56",
        "id": 3437557,
        "images": [
          {
            "dimension": "1x",
            "src": "https://ais-cf.tvnow.de/tvnow/movie/3437557/300x0/folge-56.jpg",
            "path": "https://ais-cf.tvnow.de/tvnow/movie/3437557/",
            "filename": "folge-56"
          },
          {
            "dimension": "2x",
            "src": "https://ais-cf.tvnow.de/tvnow/movie/3437557/600x0/folge-56.jpg",
            "path": "https://ais-cf.tvnow.de/tvnow/movie/3437557/",
            "filename": "folge-56"
          },
          {
            "dimension": "4x",
            "src": "https://ais-cf.tvnow.de/tvnow/movie/3437557/1200x0/folge-56.jpg",
            "path": "https://ais-cf.tvnow.de/tvnow/movie/3437557/",
            "filename": "folge-56"
          }
        ],
        "imagesHover": [
          {
            "dimension": "1x",
            "src": "https://ais-cf.tvnow.de/tvnow/movie/3437557/300x0/folge-56.jpg",
            "path": "https://ais-cf.tvnow.de/tvnow/movie/3437557/",
            "filename": "folge-56"
          },
          {
            "dimension": "2x",
            "src": "https://ais-cf.tvnow.de/tvnow/movie/3437557/600x0/folge-56.jpg",
            "path": "https://ais-cf.tvnow.de/tvnow/movie/3437557/",
            "filename": "folge-56"
          },
          {
            "dimension": "4x",
            "src": "https://ais-cf.tvnow.de/tvnow/movie/3437557/1200x0/folge-56.jpg",
            "path": "https://ais-cf.tvnow.de/tvnow/movie/3437557/",
            "filename": "folge-56"
          }
        ],
        "isPremium": false,
        "overlays": [
          "premium"
        ],
        "seoUrl": "super-toy-club",
        "subheadline": "Folge 56",
        "text": "Staffel 3, Folge 56 | Sa. 10.10.2020, 08:00 Uhr",
        "type": "show",
        "url": "/shows/super-toy-club-18042/staffel-3/episode-56-folge-56-3437557",
        "videoId": 3437557
      }
    ],
    "format_navigation": {
      "season": 3
    },
    "navigationType": "season"
  }
]