[
  {
    "ecommerce": {
      "rowCategory": "small_teaser",
      "rowId": "na",
      "rowName": "Staffel 0"
    },
    "id": null,
    "label": null,
    "moduleLayout": "format_episode",
    "moduleUrl": "/module/teaserrow/format/episode/15895",
    "type": "teaserrow",
    "items": [
      {
        "buttons": [
          {
            "display": true,
            "formatId": 15895,
            "text": null,
            "type": "favorites"
          },
          {
            "display": true,
            "text": "Jetzt ansehen",
            "type": "play",
            "url": "/filme/john-carpenters-vampires-los-muertos-15895"
          }
        ],
        "ecommerce": {
          "teaserFormatName": "John Carpenters Vampires: Los Muertos",
          "teaserId": "film_422766",
          "teaserName": "John Carpenters Vampires: Los Muertos | JOHN CARPENTERS VAMPIRES: LOS MUERTOS",
          "teaserPayType": "free",
          "teaserType": "film",
          "teaserGenre": "Action",
          "cluster": [],
          "classification": []
        },
        "fsk": {
          "isVisible": false,
          "label": "ab 0",
          "minAge": 0
        },
        "headline": "JOHN CARPENTERS VAMPIRES: LOS MUERTOS",
        "id": 422766,
        "images": [
          {
            "dimension": "1x",
            "src": "https://ais-cf.tvnow.de/tvnow/movie/422766/300x0/john-carpenters-vampires-los-muertos.jpg",
            "path": "https://ais-cf.tvnow.de/tvnow/movie/422766/",
            "filename": "john-carpenters-vampires-los-muertos"
          },
          {
            "dimension": "2x",
            "src": "https://ais-cf.tvnow.de/tvnow/movie/422766/600x0/john-carpenters-vampires-los-muertos.jpg",
            "path": "https://ais-cf.tvnow.de/tvnow/movie/422766/",
            "filename": "john-carpenters-vampires-los-muertos"
          },
          {
            "dimension": "4x",
            "src": "https://ais-cf.tvnow.de/tvnow/movie/422766/1200x0/john-carpenters-vampires-los-muertos.jpg",
            "path": "https://ais-cf.tvnow.de/tvnow/movie/422766/",
            "filename": "john-carpenters-vampires-los-muertos"
          }
        ],
        "imagesHover": [
          {
            "dimension": "1x",
            "src": "https://ais-cf.tvnow.de/tvnow/movie/422766/300x0/john-carpenters-vampires-los-muertos.jpg",
            "path": "https://ais-cf.tvnow.de/tvnow/movie/422766/",
            "filename": "john-carpenters-vampires-los-muertos"
          },
          {
            "dimension": "2x",
            "src": "https://ais-cf.tvnow.de/tvnow/movie/422766/600x0/john-carpenters-vampires-los-muertos.jpg",
            "path": "https://ais-cf.tvnow.de/tvnow/movie/422766/",
            "filename": "john-carpenters-vampires-los-muertos"
          },
          {
            "dimension": "4x",
            "src": "https://ais-cf.tvnow.de/tvnow/movie/422766/1200x0/john-carpenters-vampires-los-muertos.jpg",
            "path": "https://ais-cf.tvnow.de/tvnow/movie/422766/",
            "filename": "john-carpenters-vampires-los-muertos"
          }
        ],
        "isPremium": false,
        "overlays": [
          "premium"
        ],
        "seoUrl": "john-carpenters-vampires-los-muertos",
        "subheadline": "JOHN CARPENTERS VAMPIRES: LOS MUERTOS",
        "text": "Staffel  | WATCHBOX",
        "type": "film",
        "url": "/filme/john-carpenters-vampires-los-muertos-15895",
        "videoId": 422766
      }
    ],
    "format_navigation": {
      "season": 0
    },
    "navigationType": "season"
  }
]